Workbook

Sheet Dashboard
A1: Films Box Office Dashboard
A2: US films from 1980 to 2016 with real gross values. Hit = box office gross at or above production budget (marketing costs not included).
A4: Films analysed | C4: Hit rate | E4: Median return | G4: Total profit
A5: =COUNTIF('Cleaned Data'!$K$2:$K$4847,"Yes") | C5: =AVERAGEIFS('Cleaned Data'!$N$2:$N$4847,'Cleaned Data'!$K$2:$K$4847,"Yes") | E5: {=MEDIAN(IF('Cleaned Data'!$K$2:$K$4847="Yes",'Cleaned Data'!$M$2:$M$4847))} | G5: =SUMIFS('Cleaned Data'!$L$2:$L$4847,'Cleaned Data'!$K$2:$K$4847,"Yes")

Sheet Insights
B1: Films Box Office: Business & Human Insights
B2: Analysis set: 3,087 US films from 1980 to 2016 with real gross values. Hit = gross at or above budget. Supporting figures are in Segment Analysis.
B4: KEY TAKEAWAYS
B5: Only about half of films earn back their budget | C5: Just 55% of films took in at least their budget at the box office, and the median film returned $1.14 per $1 spent. Before marketing and distribution costs, a typical release only just breaks even, so studios rely on a few big winners to cover the rest.
B6: A few films earn most of the money | C6: The top 10% of films brought in about 41% of all box office takings. The business is driven by hits, so managing a slate as a portfolio matters more than any single title.
B7: Smaller budgets give the best returns | C7: Films under $5M had the highest median return (1.71x) and hit rate (59%). Films over $50M returned about 1.0x. Big budgets buy absolute revenue but not better odds. When they fail, the losses are huge: John Carter, Battleship, 47 Ronin and Jack the Giant Slayer each lost more than $130M.
B8: Family-friendly ratings do better | C8: G and PG films hit 63-66% of the time, compared with 53-54% for PG-13 and R. A wider audience (families who buy multiple tickets, plus repeat viewing) turns into steadier returns. R is the most common rating (44% of the set) but the least reliable.
B9: Longer films do better, partly because of what they are | C9: Films over 140 minutes had a 63% hit rate, compared with 52% for films under 90 minutes. Long films are usually prestige or franchise projects with strong source material, so length reflects confidence in the film rather than causing success.
B10: Low-budget horror stands out | C10: Paranormal Activity ($15K budget, $108M gross) and The Blair Witch Project ($60K budget, $141M gross) are the biggest return outliers. Horror is cheap to make, and fans turn out reliably and spread the word, so it is a low-risk way to try new filmmakers and ideas.
B12: HUMAN INSIGHTS (WHY AUDIENCES BEHAVE THIS WAY)
B13: Going to the cinema is a social decision | C13: G and PG films are chosen by groups, often parents with children. One "yes" sells several tickets, which explains their higher median gross despite similar budgets.
B14: Novelty and fear spread by word of mouth | C14: The low-budget horror hits sold an experience ("you have to see this") rather than stars or spectacle. Audiences reward originality when the marketing makes the film feel like an event.
B15: Spectacle alone does not win audiences | C15: Several $175M+ flops relied on effects and unfamiliar source material. Audiences pay for stories and characters they already care about, not the size of the budget.
B16: Viewers are getting more selective | C16: Median returns fell from about 3x in the 1980s to about 1.0-1.1x in the 2000s and 2010s, while releases per year grew to more than 200. More choice (and later, streaming) spreads audience attention more thinly.
B18: RECOMMENDATIONS
B19: 1. Manage the slate as a portfolio | C19: Fund several micro- and low-budget titles (under $5M) for each tentpole. Each small film costs little if it fails and can return 100x or more if it catches on.
B20: 2. Set a higher bar for $100M+ projects | C20: Approve tentpoles only with proven IP, a family-friendly rating plan and international pre-sales. Their hit rate is no better than average and the losses are the largest.
B21: 3. Aim for PG or PG-13 where the story allows | C21: Moving a film from R to PG-13 widens its audience. Only target R when the genre (horror, adult drama) needs it and the budget is kept low.
B22: 4. Invest in genres that build word of mouth | C22: Horror and original concepts at low budgets give the best return for the risk. Spend on event-style marketing rather than production.
B24: DATA CLEANING DONE
B25: Header row restored | C25: Row 1 held a garbled film record instead of column names. Proper headers were added and the record (Intolerance, 1916) was restored as a data row.
B26: 122 duplicates removed | C26: Rows repeating the same title and year were removed, keeping the first occurrence.
B27: 790 imputed gross values flagged | C27: Gross values filled with the median (25,529,689.5), plus 1 missing, are flagged in the Gross Imputed column and excluded from all revenue figures.
B28: Text "nan" placeholders blanked | C28: Missing ratings, languages and countries stored as the text "nan" are now true blanks.
B29: Analysis limited to US films from 1980 | C29: Non-US budgets are in local currencies (The Host: 12.2B KRW), and pre-1980 films are too few to compare.
B30: Known limitations | C30: Gross is box office only (no streaming, home video or marketing costs). The Polar Express gross ($0.67M) is a source error. Results show patterns, not causes.

Sheet Segment Analysis
A1: Segment Analysis: US films from 1980, real gross values only
A2: All figures are live formulas on Cleaned Data, filtered to In Analysis Set = Yes. Return = gross / budget. Hit = gross at or above budget. Median return is an array formula.
A4: Budget tier | B4: Films | C4: Hit rate | D4: Median return | E4: Total budget | F4: Total gross | G4: Total profit
A5: Under $5M | B5: =COUNTIFS('Cleaned Data'!$K$2:$K$4847,"Yes",'Cleaned Data'!$O$2:$O$4847,$A5) | C5: =IFERROR(AVERAGEIFS('Cleaned Data'!$N$2:$N$4847,'Cleaned Data'!$K$2:$K$4847,"Yes",'Cleaned Data'!$O$2:$O$4847,$A5),0) | D5: {=MEDIAN(IF(('Cleaned Data'!$K$2:$K$4847="Yes")*('Cleaned Data'!$O$2:$O$4847=$A5),'Cleaned Data'!$M$2:$M$4847))} | E5: =SUMIFS('Cleaned Data'!$I$2:$I$4847,'Cleaned Data'!$K$2:$K$4847,"Yes",'Cleaned Data'!$O$2:$O$4847,$A5) | F5: =SUMIFS('Cleaned Data'!$H$2:$H$4847,'Cleaned Data'!$K$2:$K$4847,"Yes",'Cleaned Data'!$O$2:$O$4847,$A5) | G5: =SUMIFS('Cleaned Data'!$L$2:$L$4847,'Cleaned Data'!$K$2:$K$4847,"Yes",'Cleaned Data'!$O$2:$O$4847,$A5)
A6: $5M-20M | B6: =COUNTIFS('Cleaned Data'!$K$2:$K$4847,"Yes",'Cleaned Data'!$O$2:$O$4847,$A6) | C6: =IFERROR(AVERAGEIFS('Cleaned Data'!$N$2:$N$4847,'Cleaned Data'!$K$2:$K$4847,"Yes",'Cleaned Data'!$O$2:$O$4847,$A6),0) | D6: {=MEDIAN(IF(('Cleaned Data'!$K$2:$K$4847="Yes")*('Cleaned Data'!$O$2:$O$4847=$A6),'Cleaned Data'!$M$2:$M$4847))} | E6: =SUMIFS('Cleaned Data'!$I$2:$I$4847,'Cleaned Data'!$K$2:$K$4847,"Yes",'Cleaned Data'!$O$2:$O$4847,$A6) | F6: =SUMIFS('Cleaned Data'!$H$2:$H$4847,'Cleaned Data'!$K$2:$K$4847,"Yes",'Cleaned Data'!$O$2:$O$4847,$A6) | G6: =SUMIFS('Cleaned Data'!$L$2:$L$4847,'Cleaned Data'!$K$2:$K$4847,"Yes",'Cleaned Data'!$O$2:$O$4847,$A6)
A7: $20M-50M | B7: =COUNTIFS('Cleaned Data'!$K$2:$K$4847,"Yes",'Cleaned Data'!$O$2:$O$4847,$A7) | C7: =IFERROR(AVERAGEIFS('Cleaned Data'!$N$2:$N$4847,'Cleaned Data'!$K$2:$K$4847,"Yes",'Cleaned Data'!$O$2:$O$4847,$A7),0) | D7: {=MEDIAN(IF(('Cleaned Data'!$K$2:$K$4847="Yes")*('Cleaned Data'!$O$2:$O$4847=$A7),'Cleaned Data'!$M$2:$M$4847))} | E7: =SUMIFS('Cleaned Data'!$I$2:$I$4847,'Cleaned Data'!$K$2:$K$4847,"Yes",'Cleaned Data'!$O$2:$O$4847,$A7) | F7: =SUMIFS('Cleaned Data'!$H$2:$H$4847,'Cleaned Data'!$K$2:$K$4847,"Yes",'Cleaned Data'!$O$2:$O$4847,$A7) | G7: =SUMIFS('Cleaned Data'!$L$2:$L$4847,'Cleaned Data'!$K$2:$K$4847,"Yes",'Cleaned Data'!$O$2:$O$4847,$A7)
A8: $50M-100M | B8: =COUNTIFS('Cleaned Data'!$K$2:$K$4847,"Yes",'Cleaned Data'!$O$2:$O$4847,$A8) | C8: =IFERROR(AVERAGEIFS('Cleaned Data'!$N$2:$N$4847,'Cleaned Data'!$K$2:$K$4847,"Yes",'Cleaned Data'!$O$2:$O$4847,$A8),0) | D8: {=MEDIAN(IF(('Cleaned Data'!$K$2:$K$4847="Yes")*('Cleaned Data'!$O$2:$O$4847=$A8),'Cleaned Data'!$M$2:$M$4847))} | E8: =SUMIFS('Cleaned Data'!$I$2:$I$4847,'Cleaned Data'!$K$2:$K$4847,"Yes",'Cleaned Data'!$O$2:$O$4847,$A8) | F8: =SUMIFS('Cleaned Data'!$H$2:$H$4847,'Cleaned Data'!$K$2:$K$4847,"Yes",'Cleaned Data'!$O$2:$O$4847,$A8) | G8: =SUMIFS('Cleaned Data'!$L$2:$L$4847,'Cleaned Data'!$K$2:$K$4847,"Yes",'Cleaned Data'!$O$2:$O$4847,$A8)
A9: $100M+ | B9: =COUNTIFS('Cleaned Data'!$K$2:$K$4847,"Yes",'Cleaned Data'!$O$2:$O$4847,$A9) | C9: =IFERROR(AVERAGEIFS('Cleaned Data'!$N$2:$N$4847,'Cleaned Data'!$K$2:$K$4847,"Yes",'Cleaned Data'!$O$2:$O$4847,$A9),0) | D9: {=MEDIAN(IF(('Cleaned Data'!$K$2:$K$4847="Yes")*('Cleaned Data'!$O$2:$O$4847=$A9),'Cleaned Data'!$M$2:$M$4847))} | E9: =SUMIFS('Cleaned Data'!$I$2:$I$4847,'Cleaned Data'!$K$2:$K$4847,"Yes",'Cleaned Data'!$O$2:$O$4847,$A9) | F9: =SUMIFS('Cleaned Data'!$H$2:$H$4847,'Cleaned Data'!$K$2:$K$4847,"Yes",'Cleaned Data'!$O$2:$O$4847,$A9) | G9: =SUMIFS('Cleaned Data'!$L$2:$L$4847,'Cleaned Data'!$K$2:$K$4847,"Yes",'Cleaned Data'!$O$2:$O$4847,$A9)
A11: Rating | B11: Films | C11: Hit rate | D11: Median return | E11: Total budget | F11: Total gross | G11: Total profit
A12: G | B12: =COUNTIFS('Cleaned Data'!$K$2:$K$4847,"Yes",'Cleaned Data'!$G$2:$G$4847,$A12) | C12: =IFERROR(AVERAGEIFS('Cleaned Data'!$N$2:$N$4847,'Cleaned Data'!$K$2:$K$4847,"Yes",'Cleaned Data'!$G$2:$G$4847,$A12),0) | D12: {=MEDIAN(IF(('Cleaned Data'!$K$2:$K$4847="Yes")*('Cleaned Data'!$G$2:$G$4847=$A12),'Cleaned Data'!$M$2:$M$4847))} | E12: =SUMIFS('Cleaned Data'!$I$2:$I$4847,'Cleaned Data'!$K$2:$K$4847,"Yes",'Cleaned Data'!$G$2:$G$4847,$A12) | F12: =SUMIFS('Cleaned Data'!$H$2:$H$4847,'Cleaned Data'!$K$2:$K$4847,"Yes",'Cleaned Data'!$G$2:$G$4847,$A12) | G12: =SUMIFS('Cleaned Data'!$L$2:$L$4847,'Cleaned Data'!$K$2:$K$4847,"Yes",'Cleaned Data'!$G$2:$G$4847,$A12)
A13: PG | B13: =COUNTIFS('Cleaned Data'!$K$2:$K$4847,"Yes",'Cleaned Data'!$G$2:$G$4847,$A13) | C13: =IFERROR(AVERAGEIFS('Cleaned Data'!$N$2:$N$4847,'Cleaned Data'!$K$2:$K$4847,"Yes",'Cleaned Data'!$G$2:$G$4847,$A13),0) | D13: {=MEDIAN(IF(('Cleaned Data'!$K$2:$K$4847="Yes")*('Cleaned Data'!$G$2:$G$4847=$A13),'Cleaned Data'!$M$2:$M$4847))} | E13: =SUMIFS('Cleaned Data'!$I$2:$I$4847,'Cleaned Data'!$K$2:$K$4847,"Yes",'Cleaned Data'!$G$2:$G$4847,$A13) | F13: =SUMIFS('Cleaned Data'!$H$2:$H$4847,'Cleaned Data'!$K$2:$K$4847,"Yes",'Cleaned Data'!$G$2:$G$4847,$A13) | G13: =SUMIFS('Cleaned Data'!$L$2:$L$4847,'Cleaned Data'!$K$2:$K$4847,"Yes",'Cleaned Data'!$G$2:$G$4847,$A13)
A14: PG-13 | B14: =COUNTIFS('Cleaned Data'!$K$2:$K$4847,"Yes",'Cleaned Data'!$G$2:$G$4847,$A14) | C14: =IFERROR(AVERAGEIFS('Cleaned Data'!$N$2:$N$4847,'Cleaned Data'!$K$2:$K$4847,"Yes",'Cleaned Data'!$G$2:$G$4847,$A14),0) | D14: {=MEDIAN(IF(('Cleaned Data'!$K$2:$K$4847="Yes")*('Cleaned Data'!$G$2:$G$4847=$A14),'Cleaned Data'!$M$2:$M$4847))} | E14: =SUMIFS('Cleaned Data'!$I$2:$I$4847,'Cleaned Data'!$K$2:$K$4847,"Yes",'Cleaned Data'!$G$2:$G$4847,$A14) | F14: =SUMIFS('Cleaned Data'!$H$2:$H$4847,'Cleaned Data'!$K$2:$K$4847,"Yes",'Cleaned Data'!$G$2:$G$4847,$A14) | G14: =SUMIFS('Cleaned Data'!$L$2:$L$4847,'Cleaned Data'!$K$2:$K$4847,"Yes",'Cleaned Data'!$G$2:$G$4847,$A14)
A15: R | B15: =COUNTIFS('Cleaned Data'!$K$2:$K$4847,"Yes",'Cleaned Data'!$G$2:$G$4847,$A15) | C15: =IFERROR(AVERAGEIFS('Cleaned Data'!$N$2:$N$4847,'Cleaned Data'!$K$2:$K$4847,"Yes",'Cleaned Data'!$G$2:$G$4847,$A15),0) | D15: {=MEDIAN(IF(('Cleaned Data'!$K$2:$K$4847="Yes")*('Cleaned Data'!$G$2:$G$4847=$A15),'Cleaned Data'!$M$2:$M$4847))} | E15: =SUMIFS('Cleaned Data'!$I$2:$I$4847,'Cleaned Data'!$K$2:$K$4847,"Yes",'Cleaned Data'!$G$2:$G$4847,$A15) | F15: =SUMIFS('Cleaned Data'!$H$2:$H$4847,'Cleaned Data'!$K$2:$K$4847,"Yes",'Cleaned Data'!$G$2:$G$4847,$A15) | G15: =SUMIFS('Cleaned Data'!$L$2:$L$4847,'Cleaned Data'!$K$2:$K$4847,"Yes",'Cleaned Data'!$G$2:$G$4847,$A15)
A17: Runtime (min) | B17: Films | C17: Hit rate | D17: Median return | E17: Total budget | F17: Total gross | G17: Total profit
A18: 90 or less | B18: =COUNTIFS('Cleaned Data'!$K$2:$K$4847,"Yes",'Cleaned Data'!$P$2:$P$4847,$A18) | C18: =IFERROR(AVERAGEIFS('Cleaned Data'!$N$2:$N$4847,'Cleaned Data'!$K$2:$K$4847,"Yes",'Cleaned Data'!$P$2:$P$4847,$A18),0) | D18: {=MEDIAN(IF(('Cleaned Data'!$K$2:$K$4847="Yes")*('Cleaned Data'!$P$2:$P$4847=$A18),'Cleaned Data'!$M$2:$M$4847))} | E18: =SUMIFS('Cleaned Data'!$I$2:$I$4847,'Cleaned Data'!$K$2:$K$4847,"Yes",'Cleaned Data'!$P$2:$P$4847,$A18) | F18: =SUMIFS('Cleaned Data'!$H$2:$H$4847,'Cleaned Data'!$K$2:$K$4847,"Yes",'Cleaned Data'!$P$2:$P$4847,$A18) | G18: =SUMIFS('Cleaned Data'!$L$2:$L$4847,'Cleaned Data'!$K$2:$K$4847,"Yes",'Cleaned Data'!$P$2:$P$4847,$A18)
A19: 91-105 | B19: =COUNTIFS('Cleaned Data'!$K$2:$K$4847,"Yes",'Cleaned Data'!$P$2:$P$4847,$A19) | C19: =IFERROR(AVERAGEIFS('Cleaned Data'!$N$2:$N$4847,'Cleaned Data'!$K$2:$K$4847,"Yes",'Cleaned Data'!$P$2:$P$4847,$A19),0) | D19: {=MEDIAN(IF(('Cleaned Data'!$K$2:$K$4847="Yes")*('Cleaned Data'!$P$2:$P$4847=$A19),'Cleaned Data'!$M$2:$M$4847))} | E19: =SUMIFS('Cleaned Data'!$I$2:$I$4847,'Cleaned Data'!$K$2:$K$4847,"Yes",'Cleaned Data'!$P$2:$P$4847,$A19) | F19: =SUMIFS('Cleaned Data'!$H$2:$H$4847,'Cleaned Data'!$K$2:$K$4847,"Yes",'Cleaned Data'!$P$2:$P$4847,$A19) | G19: =SUMIFS('Cleaned Data'!$L$2:$L$4847,'Cleaned Data'!$K$2:$K$4847,"Yes",'Cleaned Data'!$P$2:$P$4847,$A19)
A20: 106-120 | B20: =COUNTIFS('Cleaned Data'!$K$2:$K$4847,"Yes",'Cleaned Data'!$P$2:$P$4847,$A20) | C20: =IFERROR(AVERAGEIFS('Cleaned Data'!$N$2:$N$4847,'Cleaned Data'!$K$2:$K$4847,"Yes",'Cleaned Data'!$P$2:$P$4847,$A20),0) | D20: {=MEDIAN(IF(('Cleaned Data'!$K$2:$K$4847="Yes")*('Cleaned Data'!$P$2:$P$4847=$A20),'Cleaned Data'!$M$2:$M$4847))} | E20: =SUMIFS('Cleaned Data'!$I$2:$I$4847,'Cleaned Data'!$K$2:$K$4847,"Yes",'Cleaned Data'!$P$2:$P$4847,$A20) | F20: =SUMIFS('Cleaned Data'!$H$2:$H$4847,'Cleaned Data'!$K$2:$K$4847,"Yes",'Cleaned Data'!$P$2:$P$4847,$A20) | G20: =SUMIFS('Cleaned Data'!$L$2:$L$4847,'Cleaned Data'!$K$2:$K$4847,"Yes",'Cleaned Data'!$P$2:$P$4847,$A20)
A21: 121-140 | B21: =COUNTIFS('Cleaned Data'!$K$2:$K$4847,"Yes",'Cleaned Data'!$P$2:$P$4847,$A21) | C21: =IFERROR(AVERAGEIFS('Cleaned Data'!$N$2:$N$4847,'Cleaned Data'!$K$2:$K$4847,"Yes",'Cleaned Data'!$P$2:$P$4847,$A21),0) | D21: {=MEDIAN(IF(('Cleaned Data'!$K$2:$K$4847="Yes")*('Cleaned Data'!$P$2:$P$4847=$A21),'Cleaned Data'!$M$2:$M$4847))} | E21: =SUMIFS('Cleaned Data'!$I$2:$I$4847,'Cleaned Data'!$K$2:$K$4847,"Yes",'Cleaned Data'!$P$2:$P$4847,$A21) | F21: =SUMIFS('Cleaned Data'!$H$2:$H$4847,'Cleaned Data'!$K$2:$K$4847,"Yes",'Cleaned Data'!$P$2:$P$4847,$A21) | G21: =SUMIFS('Cleaned Data'!$L$2:$L$4847,'Cleaned Data'!$K$2:$K$4847,"Yes",'Cleaned Data'!$P$2:$P$4847,$A21)
A22: Over 140 | B22: =COUNTIFS('Cleaned Data'!$K$2:$K$4847,"Yes",'Cleaned Data'!$P$2:$P$4847,$A22) | C22: =IFERROR(AVERAGEIFS('Cleaned Data'!$N$2:$N$4847,'Cleaned Data'!$K$2:$K$4847,"Yes",'Cleaned Data'!$P$2:$P$4847,$A22),0) | D22: {=MEDIAN(IF(('Cleaned Data'!$K$2:$K$4847="Yes")*('Cleaned Data'!$P$2:$P$4847=$A22),'Cleaned Data'!$M$2:$M$4847))} | E22: =SUMIFS('Cleaned Data'!$I$2:$I$4847,'Cleaned Data'!$K$2:$K$4847,"Yes",'Cleaned Data'!$P$2:$P$4847,$A22) | F22: =SUMIFS('Cleaned Data'!$H$2:$H$4847,'Cleaned Data'!$K$2:$K$4847,"Yes",'Cleaned Data'!$P$2:$P$4847,$A22) | G22: =SUMIFS('Cleaned Data'!$L$2:$L$4847,'Cleaned Data'!$K$2:$K$4847,"Yes",'Cleaned Data'!$P$2:$P$4847,$A22)
A24: Decade | B24: Films | C24: Hit rate | D24: Median return | E24: Total budget | F24: Total gross | G24: Total profit
A25: 1980 | B25: =COUNTIFS('Cleaned Data'!$K$2:$K$4847,"Yes",'Cleaned Data'!$Q$2:$Q$4847,$A25) | C25: =IFERROR(AVERAGEIFS('Cleaned Data'!$N$2:$N$4847,'Cleaned Data'!$K$2:$K$4847,"Yes",'Cleaned Data'!$Q$2:$Q$4847,$A25),0) | D25: {=MEDIAN(IF(('Cleaned Data'!$K$2:$K$4847="Yes")*('Cleaned Data'!$Q$2:$Q$4847=$A25),'Cleaned Data'!$M$2:$M$4847))} | E25: =SUMIFS('Cleaned Data'!$I$2:$I$4847,'Cleaned Data'!$K$2:$K$4847,"Yes",'Cleaned Data'!$Q$2:$Q$4847,$A25) | F25: =SUMIFS('Cleaned Data'!$H$2:$H$4847,'Cleaned Data'!$K$2:$K$4847,"Yes",'Cleaned Data'!$Q$2:$Q$4847,$A25) | G25: =SUMIFS('Cleaned Data'!$L$2:$L$4847,'Cleaned Data'!$K$2:$K$4847,"Yes",'Cleaned Data'!$Q$2:$Q$4847,$A25)
A26: 1990 | B26: =COUNTIFS('Cleaned Data'!$K$2:$K$4847,"Yes",'Cleaned Data'!$Q$2:$Q$4847,$A26) | C26: =IFERROR(AVERAGEIFS('Cleaned Data'!$N$2:$N$4847,'Cleaned Data'!$K$2:$K$4847,"Yes",'Cleaned Data'!$Q$2:$Q$4847,$A26),0) | D26: {=MEDIAN(IF(('Cleaned Data'!$K$2:$K$4847="Yes")*('Cleaned Data'!$Q$2:$Q$4847=$A26),'Cleaned Data'!$M$2:$M$4847))} | E26: =SUMIFS('Cleaned Data'!$I$2:$I$4847,'Cleaned Data'!$K$2:$K$4847,"Yes",'Cleaned Data'!$Q$2:$Q$4847,$A26) | F26: =SUMIFS('Cleaned Data'!$H$2:$H$4847,'Cleaned Data'!$K$2:$K$4847,"Yes",'Cleaned Data'!$Q$2:$Q$4847,$A26) | G26: =SUMIFS('Cleaned Data'!$L$2:$L$4847,'Cleaned Data'!$K$2:$K$4847,"Yes",'Cleaned Data'!$Q$2:$Q$4847,$A26)
A27: 2000 | B27: =COUNTIFS('Cleaned Data'!$K$2:$K$4847,"Yes",'Cleaned Data'!$Q$2:$Q$4847,$A27) | C27: =IFERROR(AVERAGEIFS('Cleaned Data'!$N$2:$N$4847,'Cleaned Data'!$K$2:$K$4847,"Yes",'Cleaned Data'!$Q$2:$Q$4847,$A27),0) | D27: {=MEDIAN(IF(('Cleaned Data'!$K$2:$K$4847="Yes")*('Cleaned Data'!$Q$2:$Q$4847=$A27),'Cleaned Data'!$M$2:$M$4847))} | E27: =SUMIFS('Cleaned Data'!$I$2:$I$4847,'Cleaned Data'!$K$2:$K$4847,"Yes",'Cleaned Data'!$Q$2:$Q$4847,$A27) | F27: =SUMIFS('Cleaned Data'!$H$2:$H$4847,'Cleaned Data'!$K$2:$K$4847,"Yes",'Cleaned Data'!$Q$2:$Q$4847,$A27) | G27: =SUMIFS('Cleaned Data'!$L$2:$L$4847,'Cleaned Data'!$K$2:$K$4847,"Yes",'Cleaned Data'!$Q$2:$Q$4847,$A27)
A28: 2010 | B28: =COUNTIFS('Cleaned Data'!$K$2:$K$4847,"Yes",'Cleaned Data'!$Q$2:$Q$4847,$A28) | C28: =IFERROR(AVERAGEIFS('Cleaned Data'!$N$2:$N$4847,'Cleaned Data'!$K$2:$K$4847,"Yes",'Cleaned Data'!$Q$2:$Q$4847,$A28),0) | D28: {=MEDIAN(IF(('Cleaned Data'!$K$2:$K$4847="Yes")*('Cleaned Data'!$Q$2:$Q$4847=$A28),'Cleaned Data'!$M$2:$M$4847))} | E28: =SUMIFS('Cleaned Data'!$I$2:$I$4847,'Cleaned Data'!$K$2:$K$4847,"Yes",'Cleaned Data'!$Q$2:$Q$4847,$A28) | F28: =SUMIFS('Cleaned Data'!$H$2:$H$4847,'Cleaned Data'!$K$2:$K$4847,"Yes",'Cleaned Data'!$Q$2:$Q$4847,$A28) | G28: =SUMIFS('Cleaned Data'!$L$2:$L$4847,'Cleaned Data'!$K$2:$K$4847,"Yes",'Cleaned Data'!$Q$2:$Q$4847,$A28)

Sheet Data Quality
A1: Data Quality Log
A3: Check | B3: Result | C3: Action taken
A4: Films in cleaned dataset | B4: =COUNTA('Cleaned Data'!B2:B4847) | C4: Source had 4,968 records; header row restored
A5: Duplicate title + year rows removed | B5: 122 | C5: Removed in cleaning (kept first occurrence). Hardcoded: count from the cleaning script
A6: Gross filled with median (25,529,689.5) or missing | B6: =COUNTIF('Cleaned Data'!J2:J4847,"Yes") | C6: Flagged in Gross Imputed and excluded from revenue analysis
A7: Share of films with imputed gross | B7: =B6/B4 | C7: Too large to ignore: it would bias averages toward the median
A8: Budget exactly 20,000,000 | B8: =COUNTIF('Cleaned Data'!I2:I4847,20000000) | C8: Kept: a common real budget, but may hide more imputation
A9: Budgets above 1 billion (local currency) | B9: =COUNTIF('Cleaned Data'!I2:I4847,">1000000000") | C9: Non-US budgets in KRW/JPY/HUF; analysis limited to US films
A10: Runtime under 40 minutes | B10: =COUNTIF('Cleaned Data'!E2:E4847,"<40") | C10: Kept: shorts or entry errors, small effect on results
A11: Missing rating | B11: =COUNTBLANK('Cleaned Data'!G2:G4847) | C11: Kept: shown as blank; excluded from the rating segment
A12: Missing language | B12: =COUNTBLANK('Cleaned Data'!F2:F4847) | C12: Text "nan" placeholders converted to blanks
A13: Films in analysis set | B13: =COUNTIF('Cleaned Data'!K2:K4847,"Yes") | C13: US, 1980 or later, real gross
A15: Known value error: The Polar Express (2004) shows a gross of $0.67M; the real US gross was over $180M. Left as-is to keep the source traceable.

Sheet Cleaned Data
A1: ID | B1: Title | C1: Year | D1: Country | E1: Duration (min) | F1: Language | G1: Rating | H1: Gross (USD) | I1: Budget (local currency) | J1: Gross Imputed | K1: In Analysis Set | L1: Profit | M1: Return (x) | N1: Hit | O1: Budget Tier | P1: Runtime Band | Q1: Decade
A2: 1 | B2: Intolerance: Love's Struggle Throughout the Ages | C2: 1916 | D2: USA | E2: 123 | G2: Not Rated | I2: 385907 | J2: =IF(OR(H2="",H2=25529689.5),"Yes","No") | K2: =IF(AND(D2="USA",C2>=1980,J2="No"),"Yes","No") | L2: =IF(J2="Yes","",H2-I2) | M2: =IF(OR(J2="Yes",I2=0),"",H2/I2) | N2: =IF(J2="Yes","",IF(H2>=I2,1,0)) | O2: =IF(I2<=5000000,"Under $5M",IF(I2<=20000000,"$5M-20M",IF(I2<=50000000,"$20M-50M",IF(I2<=100000000,"$50M-100M","$100M+")))) | P2: =IF(E2<=90,"90 or less",IF(E2<=105,"91-105",IF(E2<=120,"106-120",IF(E2<=140,"121-140","Over 140")))) | Q2: =INT(C2/10)*10
A3: 2 | B3: Over the Hill to the Poorhouse | C3: 1920 | D3: USA | E3: 110 | H3: 3000000 | I3: 100000 | J3: =IF(OR(H3="",H3=25529689.5),"Yes","No") | K3: =IF(AND(D3="USA",C3>=1980,J3="No"),"Yes","No") | L3: =IF(J3="Yes","",H3-I3) | M3: =IF(OR(J3="Yes",I3=0),"",H3/I3) | N3: =IF(J3="Yes","",IF(H3>=I3,1,0)) | O3: =IF(I3<=5000000,"Under $5M",IF(I3<=20000000,"$5M-20M",IF(I3<=50000000,"$20M-50M",IF(I3<=100000000,"$50M-100M","$100M+")))) | P3: =IF(E3<=90,"90 or less",IF(E3<=105,"91-105",IF(E3<=120,"106-120",IF(E3<=140,"121-140","Over 140")))) | Q3: =INT(C3/10)*10
A4: 3 | B4: The Big Parade | C4: 1925 | D4: USA | E4: 151 | G4: Not Rated | H4: 25529690 | I4: 245000 | J4: =IF(OR(H4="",H4=25529689.5),"Yes","No") | K4: =IF(AND(D4="USA",C4>=1980,J4="No"),"Yes","No") | L4: =IF(J4="Yes","",H4-I4) | M4: =IF(OR(J4="Yes",I4=0),"",H4/I4) | N4: =IF(J4="Yes","",IF(H4>=I4,1,0)) | O4: =IF(I4<=5000000,"Under $5M",IF(I4<=20000000,"$5M-20M",IF(I4<=50000000,"$20M-50M",IF(I4<=100000000,"$50M-100M","$100M+")))) | P4: =IF(E4<=90,"90 or less",IF(E4<=105,"91-105",IF(E4<=120,"106-120",IF(E4<=140,"121-140","Over 140")))) | Q4: =INT(C4/10)*10
A5: 4 | B5: Metropolis | C5: 1927 | D5: Germany | E5: 145 | F5: German | G5: Not Rated | H5: 26435 | I5: 6000000 | J5: =IF(OR(H5="",H5=25529689.5),"Yes","No") | K5: =IF(AND(D5="USA",C5>=1980,J5="No"),"Yes","No") | L5: =IF(J5="Yes","",H5-I5) | M5: =IF(OR(J5="Yes",I5=0),"",H5/I5) | N5: =IF(J5="Yes","",IF(H5>=I5,1,0)) | O5: =IF(I5<=5000000,"Under $5M",IF(I5<=20000000,"$5M-20M",IF(I5<=50000000,"$20M-50M",IF(I5<=100000000,"$50M-100M","$100M+")))) | P5: =IF(E5<=90,"90 or less",IF(E5<=105,"91-105",IF(E5<=120,"106-120",IF(E5<=140,"121-140","Over 140")))) | Q5: =INT(C5/10)*10
A6: 5 | B6: Pandora's Box | C6: 1929 | D6: Germany | E6: 110 | F6: German | G6: Not Rated | H6: 9950 | I6: 20000000 | J6: =IF(OR(H6="",H6=25529689.5),"Yes","No") | K6: =IF(AND(D6="USA",C6>=1980,J6="No"),"Yes","No") | L6: =IF(J6="Yes","",H6-I6) | M6: =IF(OR(J6="Yes",I6=0),"",H6/I6) | N6: =IF(J6="Yes","",IF(H6>=I6,1,0)) | O6: =IF(I6<=5000000,"Under $5M",IF(I6<=20000000,"$5M-20M",IF(I6<=50000000,"$20M-50M",IF(I6<=100000000,"$50M-100M","$100M+")))) | P6: =IF(E6<=90,"90 or less",IF(E6<=105,"91-105",IF(E6<=120,"106-120",IF(E6<=140,"121-140","Over 140")))) | Q6: =INT(C6/10)*10
A7: 6 | B7: The Broadway Melody | C7: 1929 | D7: USA | E7: 100 | F7: English | G7: Passed | H7: 2808000 | I7: 379000 | J7: =IF(OR(H7="",H7=25529689.5),"Yes","No") | K7: =IF(AND(D7="USA",C7>=1980,J7="No"),"Yes","No") | L7: =IF(J7="Yes","",H7-I7) | M7: =IF(OR(J7="Yes",I7=0),"",H7/I7) | N7: =IF(J7="Yes","",IF(H7>=I7,1,0)) | O7: =IF(I7<=5000000,"Under $5M",IF(I7<=20000000,"$5M-20M",IF(I7<=50000000,"$20M-50M",IF(I7<=100000000,"$50M-100M","$100M+")))) | P7: =IF(E7<=90,"90 or less",IF(E7<=105,"91-105",IF(E7<=120,"106-120",IF(E7<=140,"121-140","Over 140")))) | Q7: =INT(C7/10)*10
A8: 7 | B8: Hell's Angels | C8: 1930 | D8: USA | E8: 96 | F8: English | G8: Passed | H8: 25529690 | I8: 3950000 | J8: =IF(OR(H8="",H8=25529689.5),"Yes","No") | K8: =IF(AND(D8="USA",C8>=1980,J8="No"),"Yes","No") | L8: =IF(J8="Yes","",H8-I8) | M8: =IF(OR(J8="Yes",I8=0),"",H8/I8) | N8: =IF(J8="Yes","",IF(H8>=I8,1,0)) | O8: =IF(I8<=5000000,"Under $5M",IF(I8<=20000000,"$5M-20M",IF(I8<=50000000,"$20M-50M",IF(I8<=100000000,"$50M-100M","$100M+")))) | P8: =IF(E8<=90,"90 or less",IF(E8<=105,"91-105",IF(E8<=120,"106-120",IF(E8<=140,"121-140","Over 140")))) | Q8: =INT(C8/10)*10
A9: 8 | B9: A Farewell to Arms | C9: 1932 | D9: USA | E9: 79 | F9: English | G9: Unrated | H9: 25529690 | I9: 800000 | J9: =IF(OR(H9="",H9=25529689.5),"Yes","No") | K9: =IF(AND(D9="USA",C9>=1980,J9="No"),"Yes","No") | L9: =IF(J9="Yes","",H9-I9) | M9: =IF(OR(J9="Yes",I9=0),"",H9/I9) | N9: =IF(J9="Yes","",IF(H9>=I9,1,0)) | O9: =IF(I9<=5000000,"Under $5M",IF(I9<=20000000,"$5M-20M",IF(I9<=50000000,"$20M-50M",IF(I9<=100000000,"$50M-100M","$100M+")))) | P9: =IF(E9<=90,"90 or less",IF(E9<=105,"91-105",IF(E9<=120,"106-120",IF(E9<=140,"121-140","Over 140")))) | Q9: =INT(C9/10)*10
A10: 9 | B10: 42nd Street | C10: 1933 | D10: USA | E10: 89 | F10: English | G10: Unrated | H10: 2300000 | I10: 439000 | J10: =IF(OR(H10="",H10=25529689.5),"Yes","No") | K10: =IF(AND(D10="USA",C10>=1980,J10="No"),"Yes","No") | L10: =IF(J10="Yes","",H10-I10) | M10: =IF(OR(J10="Yes",I10=0),"",H10/I10) | N10: =IF(J10="Yes","",IF(H10>=I10,1,0)) | O10: =IF(I10<=5000000,"Under $5M",IF(I10<=20000000,"$5M-20M",IF(I10<=50000000,"$20M-50M",IF(I10<=100000000,"$50M-100M","$100M+")))) | P10: =IF(E10<=90,"90 or less",IF(E10<=105,"91-105",IF(E10<=120,"106-120",IF(E10<=140,"121-140","Over 140")))) | Q10: =INT(C10/10)*10
A11: 10 | B11: She Done Him Wrong | C11: 1933 | D11: USA | E11: 66 | F11: English | G11: Approved | H11: 25529690 | I11: 200000 | J11: =IF(OR(H11="",H11=25529689.5),"Yes","No") | K11: =IF(AND(D11="USA",C11>=1980,J11="No"),"Yes","No") | L11: =IF(J11="Yes","",H11-I11) | M11: =IF(OR(J11="Yes",I11=0),"",H11/I11) | N11: =IF(J11="Yes","",IF(H11>=I11,1,0)) | O11: =IF(I11<=5000000,"Under $5M",IF(I11<=20000000,"$5M-20M",IF(I11<=50000000,"$20M-50M",IF(I11<=100000000,"$50M-100M","$100M+")))) | P11: =IF(E11<=90,"90 or less",IF(E11<=105,"91-105",IF(E11<=120,"106-120",IF(E11<=140,"121-140","Over 140")))) | Q11: =INT(C11/10)*10
A12: 11 | B12: It Happened One Night | C12: 1934 | D12: USA | E12: 65 | F12: English | G12: Unrated | H12: 25529690 | I12: 325000 | J12: =IF(OR(H12="",H12=25529689.5),"Yes","No") | K12: =IF(AND(D12="USA",C12>=1980,J12="No"),"Yes","No") | L12: =IF(J12="Yes","",H12-I12) | M12: =IF(OR(J12="Yes",I12=0),"",H12/I12) | N12: =IF(J12="Yes","",IF(H12>=I12,1,0)) | O12: =IF(I12<=5000000,"Under $5M",IF(I12<=20000000,"$5M-20M",IF(I12<=50000000,"$20M-50M",IF(I12<=100000000,"$50M-100M","$100M+")))) | P12: =IF(E12<=90,"90 or less",IF(E12<=105,"91-105",IF(E12<=120,"106-120",IF(E12<=140,"121-140","Over 140")))) | Q12: =INT(C12/10)*10
A13: 12 | B13: Top Hat | C13: 1935 | D13: USA | E13: 81 | F13: English | G13: Approved | H13: 3000000 | I13: 609000 | J13: =IF(OR(H13="",H13=25529689.5),"Yes","No") | K13: =IF(AND(D13="USA",C13>=1980,J13="No"),"Yes","No") | L13: =IF(J13="Yes","",H13-I13) | M13: =IF(OR(J13="Yes",I13=0),"",H13/I13) | N13: =IF(J13="Yes","",IF(H13>=I13,1,0)) | O13: =IF(I13<=5000000,"Under $5M",IF(I13<=20000000,"$5M-20M",IF(I13<=50000000,"$20M-50M",IF(I13<=100000000,"$50M-100M","$100M+")))) | P13: =IF(E13<=90,"90 or less",IF(E13<=105,"91-105",IF(E13<=120,"106-120",IF(E13<=140,"121-140","Over 140")))) | Q13: =INT(C13/10)*10
A14: 13 | B14: Modern Times | C14: 1936 | D14: USA | E14: 87 | F14: English | G14: G | H14: 163245 | I14: 1500000 | J14: =IF(OR(H14="",H14=25529689.5),"Yes","No") | K14: =IF(AND(D14="USA",C14>=1980,J14="No"),"Yes","No") | L14: =IF(J14="Yes","",H14-I14) | M14: =IF(OR(J14="Yes",I14=0),"",H14/I14) | N14: =IF(J14="Yes","",IF(H14>=I14,1,0)) | O14: =IF(I14<=5000000,"Under $5M",IF(I14<=20000000,"$5M-20M",IF(I14<=50000000,"$20M-50M",IF(I14<=100000000,"$50M-100M","$100M+")))) | P14: =IF(E14<=90,"90 or less",IF(E14<=105,"91-105",IF(E14<=120,"106-120",IF(E14<=140,"121-140","Over 140")))) | Q14: =INT(C14/10)*10
A15: 14 | B15: The Charge of the Light Brigade | C15: 1936 | D15: USA | E15: 100 | F15: English | G15: Approved | H15: 25529690 | I15: 1200000 | J15: =IF(OR(H15="",H15=25529689.5),"Yes","No") | K15: =IF(AND(D15="USA",C15>=1980,J15="No"),"Yes","No") | L15: =IF(J15="Yes","",H15-I15) | M15: =IF(OR(J15="Yes",I15=0),"",H15/I15) | N15: =IF(J15="Yes","",IF(H15>=I15,1,0)) | O15: =IF(I15<=5000000,"Under $5M",IF(I15<=20000000,"$5M-20M",IF(I15<=50000000,"$20M-50M",IF(I15<=100000000,"$50M-100M","$100M+")))) | P15: =IF(E15<=90,"90 or less",IF(E15<=105,"91-105",IF(E15<=120,"106-120",IF(E15<=140,"121-140","Over 140")))) | Q15: =INT(C15/10)*10
A16: 15 | B16: Snow White and the Seven Dwarfs | C16: 1937 | D16: USA | E16: 83 | F16: English | G16: Approved | H16: 184925485 | I16: 2000000 | J16: =IF(OR(H16="",H16=25529689.5),"Yes","No") | K16: =IF(AND(D16="USA",C16>=1980,J16="No"),"Yes","No") | L16: =IF(J16="Yes","",H16-I16) | M16: =IF(OR(J16="Yes",I16=0),"",H16/I16) | N16: =IF(J16="Yes","",IF(H16>=I16,1,0)) | O16: =IF(I16<=5000000,"Under $5M",IF(I16<=20000000,"$5M-20M",IF(I16<=50000000,"$20M-50M",IF(I16<=100000000,"$50M-100M","$100M+")))) | P16: =IF(E16<=90,"90 or less",IF(E16<=105,"91-105",IF(E16<=120,"106-120",IF(E16<=140,"121-140","Over 140")))) | Q16: =INT(C16/10)*10
... A51: 50 | B51: Show Boat | C51: 1951 | D51: USA | E51: 108 | F51: English | G51: Approved | H51: 25529690 | I51: 2295429 | J51: =IF(OR(H51="",H51=25529689.5),"Yes","No") | K51: =IF(AND(D51="USA",C51>=1980,J51="No"),"Yes","No") | L51: =IF(J51="Yes","",H51-I51) | M51: =IF(OR(J51="Yes",I51=0),"",H51/I51) | N51: =IF(J51="Yes","",IF(H51>=I51,1,0)) | O51: =IF(I51<=5000000,"Under $5M",IF(I51<=20000000,"$5M-20M",IF(I51<=50000000,"$20M-50M",IF(I51<=100000000,"$50M-100M","$100M+")))) | P51: =IF(E51<=90,"90 or less",IF(E51<=105,"91-105",IF(E51<=120,"106-120",IF(E51<=140,"121-140","Over 140")))) | Q51: =INT(C51/10)*10
A52: 51 | B52: Deadline - U.S.A. | C52: 1952 | D52: USA | E52: 87 | F52: English | H52: 25529690 | I52: 20000000 | J52: =IF(OR(H52="",H52=25529689.5),"Yes","No") | K52: =IF(AND(D52="USA",C52>=1980,J52="No"),"Yes","No") | L52: =IF(J52="Yes","",H52-I52) | M52: =IF(OR(J52="Yes",I52=0),"",H52/I52) | N52: =IF(J52="Yes","",IF(H52>=I52,1,0)) | O52: =IF(I52<=5000000,"Under $5M",IF(I52<=20000000,"$5M-20M",IF(I52<=50000000,"$20M-50M",IF(I52<=100000000,"$50M-100M","$100M+")))) | P52: =IF(E52<=90,"90 or less",IF(E52<=105,"91-105",IF(E52<=120,"106-120",IF(E52<=140,"121-140","Over 140")))) | Q52: =INT(C52/10)*10
A53: 52 | B53: High Noon | C53: 1952 | D53: USA | E53: 85 | F53: English | G53: PG | H53: 25529690 | I53: 750000 | J53: =IF(OR(H53="",H53=25529689.5),"Yes","No") | K53: =IF(AND(D53="USA",C53>=1980,J53="No"),"Yes","No") | L53: =IF(J53="Yes","",H53-I53) | M53: =IF(OR(J53="Yes",I53=0),"",H53/I53) | N53: =IF(J53="Yes","",IF(H53>=I53,1,0)) | O53: =IF(I53<=5000000,"Under $5M",IF(I53<=20000000,"$5M-20M",IF(I53<=50000000,"$20M-50M",IF(I53<=100000000,"$50M-100M","$100M+")))) | P53: =IF(E53<=90,"90 or less",IF(E53<=105,"91-105",IF(E53<=120,"106-120",IF(E53<=140,"121-140","Over 140")))) | Q53: =INT(C53/10)*10
A54: 53 | B54: Singin' in the Rain | C54: 1952 | D54: USA | E54: 103 | F54: English | G54: Approved | H54: 25529690 | I54: 2540800 | J54: =IF(OR(H54="",H54=25529689.5),"Yes","No") | K54: =IF(AND(D54="USA",C54>=1980,J54="No"),"Yes","No") | L54: =IF(J54="Yes","",H54-I54) | M54: =IF(OR(J54="Yes",I54=0),"",H54/I54) | N54: =IF(J54="Yes","",IF(H54>=I54,1,0)) | O54: =IF(I54<=5000000,"Under $5M",IF(I54<=20000000,"$5M-20M",IF(I54<=50000000,"$20M-50M",IF(I54<=100000000,"$50M-100M","$100M+")))) | P54: =IF(E54<=90,"90 or less",IF(E54<=105,"91-105",IF(E54<=120,"106-120",IF(E54<=140,"121-140","Over 140")))) | Q54: =INT(C54/10)*10
A55: 54 | B55: The Greatest Show on Earth | C55: 1952 | D55: USA | E55: 152 | F55: English | G55: Not Rated | H55: 36000000 | I55: 4000000 | J55: =IF(OR(H55="",H55=25529689.5),"Yes","No") | K55: =IF(AND(D55="USA",C55>=1980,J55="No"),"Yes","No") | L55: =IF(J55="Yes","",H55-I55) | M55: =IF(OR(J55="Yes",I55=0),"",H55/I55) | N55: =IF(J55="Yes","",IF(H55>=I55,1,0)) | O55: =IF(I55<=5000000,"Under $5M",IF(I55<=20000000,"$5M-20M",IF(I55<=50000000,"$20M-50M",IF(I55<=100000000,"$50M-100M","$100M+")))) | P55: =IF(E55<=90,"90 or less",IF(E55<=105,"91-105",IF(E55<=120,"106-120",IF(E55<=140,"121-140","Over 140")))) | Q55: =INT(C55/10)*10
A56: 55 | B56: From Here to Eternity | C56: 1953 | D56: USA | E56: 118 | F56: English | G56: Not Rated | H56: 25529690 | I56: 1650000 | J56: =IF(OR(H56="",H56=25529689.5),"Yes","No") | K56: =IF(AND(D56="USA",C56>=1980,J56="No"),"Yes","No") | L56: =IF(J56="Yes","",H56-I56) | M56: =IF(OR(J56="Yes",I56=0),"",H56/I56) | N56: =IF(J56="Yes","",IF(H56>=I56,1,0)) | O56: =IF(I56<=5000000,"Under $5M",IF(I56<=20000000,"$5M-20M",IF(I56<=50000000,"$20M-50M",IF(I56<=100000000,"$50M-100M","$100M+")))) | P56: =IF(E56<=90,"90 or less",IF(E56<=105,"91-105",IF(E56<=120,"106-120",IF(E56<=140,"121-140","Over 140")))) | Q56: =INT(C56/10)*10
A57: 56 | B57: Niagara | C57: 1953 | D57: USA | E57: 92 | F57: English | G57: Approved | H57: 25529690 | I57: 1250000 | J57: =IF(OR(H57="",H57=25529689.5),"Yes","No") | K57: =IF(AND(D57="USA",C57>=1980,J57="No"),"Yes","No") | L57: =IF(J57="Yes","",H57-I57) | M57: =IF(OR(J57="Yes",I57=0),"",H57/I57) | N57: =IF(J57="Yes","",IF(H57>=I57,1,0)) | O57: =IF(I57<=5000000,"Under $5M",IF(I57<=20000000,"$5M-20M",IF(I57<=50000000,"$20M-50M",IF(I57<=100000000,"$50M-100M","$100M+")))) | P57: =IF(E57<=90,"90 or less",IF(E57<=105,"91-105",IF(E57<=120,"106-120",IF(E57<=140,"121-140","Over 140")))) | Q57: =INT(C57/10)*10
A58: 57 | B58: The Beast from 20,000 Fathoms | C58: 1953 | D58: USA | E58: 80 | F58: English | G58: Approved | H58: 5000000 | I58: 210000 | J58: =IF(OR(H58="",H58=25529689.5),"Yes","No") | K58: =IF(AND(D58="USA",C58>=1980,J58="No"),"Yes","No") | L58: =IF(J58="Yes","",H58-I58) | M58: =IF(OR(J58="Yes",I58=0),"",H58/I58) | N58: =IF(J58="Yes","",IF(H58>=I58,1,0)) | O58: =IF(I58<=5000000,"Under $5M",IF(I58<=20000000,"$5M-20M",IF(I58<=50000000,"$20M-50M",IF(I58<=100000000,"$50M-100M","$100M+")))) | P58: =IF(E58<=90,"90 or less",IF(E58<=105,"91-105",IF(E58<=120,"106-120",IF(E58<=140,"121-140","Over 140")))) | Q58: =INT(C58/10)*10
A59: 58 | B59: The Robe | C59: 1953 | D59: USA | E59: 135 | F59: English | G59: Unrated | H59: 36000000 | I59: 5000000 | J59: =IF(OR(H59="",H59=25529689.5),"Yes","No") | K59: =IF(AND(D59="USA",C59>=1980,J59="No"),"Yes","No") | L59: =IF(J59="Yes","",H59-I59) | M59: =IF(OR(J59="Yes",I59=0),"",H59/I59) | N59: =IF(J59="Yes","",IF(H59>=I59,1,0)) | O59: =IF(I59<=5000000,"Under $5M",IF(I59<=20000000,"$5M-20M",IF(I59<=50000000,"$20M-50M",IF(I59<=100000000,"$50M-100M","$100M+")))) | P59: =IF(E59<=90,"90 or less",IF(E59<=105,"91-105",IF(E59<=120,"106-120",IF(E59<=140,"121-140","Over 140")))) | Q59: =INT(C59/10)*10
A60: 59 | B60: 20,000 Leagues Under the Sea | C60: 1954 | D60: USA | E60: 127 | F60: English | G60: Approved | H60: 25529690 | I60: 5000000 | J60: =IF(OR(H60="",H60=25529689.5),"Yes","No") | K60: =IF(AND(D60="USA",C60>=1980,J60="No"),"Yes","No") | L60: =IF(J60="Yes","",H60-I60) | M60: =IF(OR(J60="Yes",I60=0),"",H60/I60) | N60: =IF(J60="Yes","",IF(H60>=I60,1,0)) | O60: =IF(I60<=5000000,"Under $5M",IF(I60<=20000000,"$5M-20M",IF(I60<=50000000,"$20M-50M",IF(I60<=100000000,"$50M-100M","$100M+")))) | P60: =IF(E60<=90,"90 or less",IF(E60<=105,"91-105",IF(E60<=120,"106-120",IF(E60<=140,"121-140","Over 140")))) | Q60: =INT(C60/10)*10
A61: 61 | B61: On the Waterfront | C61: 1954 | D61: USA | E61: 108 | F61: English | G61: Not Rated | H61: 9600000 | I61: 910000 | J61: =IF(OR(H61="",H61=25529689.5),"Yes","No") | K61: =IF(AND(D61="USA",C61>=1980,J61="No"),"Yes","No") | L61: =IF(J61="Yes","",H61-I61) | M61: =IF(OR(J61="Yes",I61=0),"",H61/I61) | N61: =IF(J61="Yes","",IF(H61>=I61,1,0)) | O61: =IF(I61<=5000000,"Under $5M",IF(I61<=20000000,"$5M-20M",IF(I61<=50000000,"$20M-50M",IF(I61<=100000000,"$50M-100M","$100M+")))) | P61: =IF(E61<=90,"90 or less",IF(E61<=105,"91-105",IF(E61<=120,"106-120",IF(E61<=140,"121-140","Over 140")))) | Q61: =INT(C61/10)*10
A62: 62 | B62: Seven Samurai | C62: 1954 | D62: Japan | E62: 202 | F62: Japanese | G62: Unrated | H62: 269061 | I62: 2000000 | J62: =IF(OR(H62="",H62=25529689.5),"Yes","No") | K62: =IF(AND(D62="USA",C62>=1980,J62="No"),"Yes","No") | L62: =IF(J62="Yes","",H62-I62) | M62: =IF(OR(J62="Yes",I62=0),"",H62/I62) | N62: =IF(J62="Yes","",IF(H62>=I62,1,0)) | O62: =IF(I62<=5000000,"Under $5M",IF(I62<=20000000,"$5M-20M",IF(I62<=50000000,"$20M-50M",IF(I62<=100000000,"$50M-100M","$100M+")))) | P62: =IF(E62<=90,"90 or less",IF(E62<=105,"91-105",IF(E62<=120,"106-120",IF(E62<=140,"121-140","Over 140")))) | Q62: =INT(C62/10)*10
A63: 63 | B63: The Egyptian | C63: 1954 | D63: USA | E63: 139 | F63: English | G63: Approved | H63: 25529690 | I63: 5000000 | J63: =IF(OR(H63="",H63=25529689.5),"Yes","No") | K63: =IF(AND(D63="USA",C63>=1980,J63="No"),"Yes","No") | L63: =IF(J63="Yes","",H63-I63) | M63: =IF(OR(J63="Yes",I63=0),"",H63/I63) | N63: =IF(J63="Yes","",IF(H63>=I63,1,0)) | O63: =IF(I63<=5000000,"Under $5M",IF(I63<=20000000,"$5M-20M",IF(I63<=50000000,"$20M-50M",IF(I63<=100000000,"$50M-100M","$100M+")))) | P63: =IF(E63<=90,"90 or less",IF(E63<=105,"91-105",IF(E63<=120,"106-120",IF(E63<=140,"121-140","Over 140")))) | Q63: =INT(C63/10)*10
A64: 64 | B64: Ordet | C64: 1955 | D64: Denmark | E64: 126 | F64: Danish | G64: Not Rated | H64: 25529690 | I64: 20000000 | J64: =IF(OR(H64="",H64=25529689.5),"Yes","No") | K64: =IF(AND(D64="USA",C64>=1980,J64="No"),"Yes","No") | L64: =IF(J64="Yes","",H64-I64) | M64: =IF(OR(J64="Yes",I64=0),"",H64/I64) | N64: =IF(J64="Yes","",IF(H64>=I64,1,0)) | O64: =IF(I64<=5000000,"Under $5M",IF(I64<=20000000,"$5M-20M",IF(I64<=50000000,"$20M-50M",IF(I64<=100000000,"$50M-100M","$100M+")))) | P64: =IF(E64<=90,"90 or less",IF(E64<=105,"91-105",IF(E64<=120,"106-120",IF(E64<=140,"121-140","Over 140")))) | Q64: =INT(C64/10)*10
A65: 65 | B65: The Trouble with Harry | C65: 1955 | D65: USA | E65: 99 | F65: English | G65: Approved | H65: 25529690 | I65: 1200000 | J65: =IF(OR(H65="",H65=25529689.5),"Yes","No") | K65: =IF(AND(D65="USA",C65>=1980,J65="No"),"Yes","No") | L65: =IF(J65="Yes","",H65-I65) | M65: =IF(OR(J65="Yes",I65=0),"",H65/I65) | N65: =IF(J65="Yes","",IF(H65>=I65,1,0)) | O65: =IF(I65<=5000000,"Under $5M",IF(I65<=20000000,"$5M-20M",IF(I65<=50000000,"$20M-50M",IF(I65<=100000000,"$50M-100M","$100M+")))) | P65: =IF(E65<=90,"90 or less",IF(E65<=105,"91-105",IF(E65<=120,"106-120",IF(E65<=140,"121-140","Over 140")))) | Q65: =INT(C65/10)*10
A66: 66 | B66: Love Me Tender | C66: 1956 | D66: USA | E66: 89 | F66: English | H66: 25529690 | I66: 1000000 | J66: =IF(OR(H66="",H66=25529689.5),"Yes","No") | K66: =IF(AND(D66="USA",C66>=1980,J66="No"),"Yes","No") | L66: =IF(J66="Yes","",H66-I66) | M66: =IF(OR(J66="Yes",I66=0),"",H66/I66) | N66: =IF(J66="Yes","",IF(H66>=I66,1,0)) | O66: =IF(I66<=5000000,"Under $5M",IF(I66<=20000000,"$5M-20M",IF(I66<=50000000,"$20M-50M",IF(I66<=100000000,"$50M-100M","$100M+")))) | P66: =IF(E66<=90,"90 or less",IF(E66<=105,"91-105",IF(E66<=120,"106-120",IF(E66<=140,"121-140","Over 140")))) | Q66: =INT(C66/10)*10
A67: 67 | B67: Moby Dick | C67: 1956 | D67: USA | E67: 115 | F67: English | G67: Unrated | H67: 25529690 | I67: 4500000 | J67: =IF(OR(H67="",H67=25529689.5),"Yes","No") | K67: =IF(AND(D67="USA",C67>=1980,J67="No"),"Yes","No") | L67: =IF(J67="Yes","",H67-I67) | M67: =IF(OR(J67="Yes",I67=0),"",H67/I67) | N67: =IF(J67="Yes","",IF(H67>=I67,1,0)) | O67: =IF(I67<=5000000,"Under $5M",IF(I67<=20000000,"$5M-20M",IF(I67<=50000000,"$20M-50M",IF(I67<=100000000,"$50M-100M","$100M+")))) | P67: =IF(E67<=90,"90 or less",IF(E67<=105,"91-105",IF(E67<=120,"106-120",IF(E67<=140,"121-140","Over 140")))) | Q67: =INT(C67/10)*10
A68: 68 | B68: Trapeze | C68: 1956 | D68: USA | E68: 105 | F68: English | G68: Approved | H68: 25529690 | I68: 4000000 | J68: =IF(OR(H68="",H68=25529689.5),"Yes","No") | K68: =IF(AND(D68="USA",C68>=1980,J68="No"),"Yes","No") | L68: =IF(J68="Yes","",H68-I68) | M68: =IF(OR(J68="Yes",I68=0),"",H68/I68) | N68: =IF(J68="Yes","",IF(H68>=I68,1,0)) | O68: =IF(I68<=5000000,"Under $5M",IF(I68<=20000000,"$5M-20M",IF(I68<=50000000,"$20M-50M",IF(I68<=100000000,"$50M-100M","$100M+")))) | P68: =IF(E68<=90,"90 or less",IF(E68<=105,"91-105",IF(E68<=120,"106-120",IF(E68<=140,"121-140","Over 140")))) | Q68: =INT(C68/10)*10
A69: 69 | B69: 12 Angry Men | C69: 1957 | D69: USA | E69: 96 | F69: English | G69: Not Rated | H69: 25529690 | I69: 350000 | J69: =IF(OR(H69="",H69=25529689.5),"Yes","No") | K69: =IF(AND(D69="USA",C69>=1980,J69="No"),"Yes","No") | L69: =IF(J69="Yes","",H69-I69) | M69: =IF(OR(J69="Yes",I69=0),"",H69/I69) | N69: =IF(J69="Yes","",IF(H69>=I69,1,0)) | O69: =IF(I69<=5000000,"Under $5M",IF(I69<=20000000,"$5M-20M",IF(I69<=50000000,"$20M-50M",IF(I69<=100000000,"$50M-100M","$100M+")))) | P69: =IF(E69<=90,"90 or less",IF(E69<=105,"91-105",IF(E69<=120,"106-120",IF(E69<=140,"121-140","Over 140")))) | Q69: =INT(C69/10)*10
A70: 70 | B70: The Bridge on the River Kwai | C70: 1957 | D70: UK | E70: 161 | F70: English | G70: PG | H70: 27200000 | I70: 3000000 | J70: =IF(OR(H70="",H70=25529689.5),"Yes","No") | K70: =IF(AND(D70="USA",C70>=1980,J70="No"),"Yes","No") | L70: =IF(J70="Yes","",H70-I70) | M70: =IF(OR(J70="Yes",I70=0),"",H70/I70) | N70: =IF(J70="Yes","",IF(H70>=I70,1,0)) | O70: =IF(I70<=5000000,"Under $5M",IF(I70<=20000000,"$5M-20M",IF(I70<=50000000,"$20M-50M",IF(I70<=100000000,"$50M-100M","$100M+")))) | P70: =IF(E70<=90,"90 or less",IF(E70<=105,"91-105",IF(E70<=120,"106-120",IF(E70<=140,"121-140","Over 140")))) | Q70: =INT(C70/10)*10
A71: 71 | B71: Cat on a Hot Tin Roof | C71: 1958 | D71: USA | E71: 108 | F71: English | G71: Approved | H71: 25529690 | I71: 3000000 | J71: =IF(OR(H71="",H71=25529689.5),"Yes","No") | K71: =IF(AND(D71="USA",C71>=1980,J71="No"),"Yes","No") | L71: =IF(J71="Yes","",H71-I71) | M71: =IF(OR(J71="Yes",I71=0),"",H71/I71) | N71: =IF(J71="Yes","",IF(H71>=I71,1,0)) | O71: =IF(I71<=5000000,"Under $5M",IF(I71<=20000000,"$5M-20M",IF(I71<=50000000,"$20M-50M",IF(I71<=100000000,"$50M-100M","$100M+")))) | P71: =IF(E71<=90,"90 or less",IF(E71<=105,"91-105",IF(E71<=120,"106-120",IF(E71<=140,"121-140","Over 140")))) | Q71: =INT(C71/10)*10
A72: 72 | B72: Solomon and Sheba | C72: 1959 | D72: USA | E72: 141 | F72: English | H72: 25529690 | I72: 5000000 | J72: =IF(OR(H72="",H72=25529689.5),"Yes","No") | K72: =IF(AND(D72="USA",C72>=1980,J72="No"),"Yes","No") | L72: =IF(J72="Yes","",H72-I72) | M72: =IF(OR(J72="Yes",I72=0),"",H72/I72) | N72: =IF(J72="Yes","",IF(H72>=I72,1,0)) | O72: =IF(I72<=5000000,"Under $5M",IF(I72<=20000000,"$5M-20M",IF(I72<=50000000,"$20M-50M",IF(I72<=100000000,"$50M-100M","$100M+")))) | P72: =IF(E72<=90,"90 or less",IF(E72<=105,"91-105",IF(E72<=120,"106-120",IF(E72<=140,"121-140","Over 140")))) | Q72: =INT(C72/10)*10
A73: 73 | B73: Some Like It Hot | C73: 1959 | D73: USA | E73: 120 | F73: English | G73: Not Rated | H73: 25000000 | I73: 2883848 | J73: =IF(OR(H73="",H73=25529689.5),"Yes","No") | K73: =IF(AND(D73="USA",C73>=1980,J73="No"),"Yes","No") | L73: =IF(J73="Yes","",H73-I73) | M73: =IF(OR(J73="Yes",I73=0),"",H73/I73) | N73: =IF(J73="Yes","",IF(H73>=I73,1,0)) | O73: =IF(I73<=5000000,"Under $5M",IF(I73<=20000000,"$5M-20M",IF(I73<=50000000,"$20M-50M",IF(I73<=100000000,"$50M-100M","$100M+")))) | P73: =IF(E73<=90,"90 or less",IF(E73<=105,"91-105",IF(E73<=120,"106-120",IF(E73<=140,"121-140","Over 140")))) | Q73: =INT(C73/10)*10
A74: 74 | B74: The Nun's Story | C74: 1959 | D74: USA | E74: 149 | F74: English | G74: Not Rated | H74: 25529690 | I74: 3500000 | J74: =IF(OR(H74="",H74=25529689.5),"Yes","No") | K74: =IF(AND(D74="USA",C74>=1980,J74="No"),"Yes","No") | L74: =IF(J74="Yes","",H74-I74) | M74: =IF(OR(J74="Yes",I74=0),"",H74/I74) | N74: =IF(J74="Yes","",IF(H74>=I74,1,0)) | O74: =IF(I74<=5000000,"Under $5M",IF(I74<=20000000,"$5M-20M",IF(I74<=50000000,"$20M-50M",IF(I74<=100000000,"$50M-100M","$100M+")))) | P74: =IF(E74<=90,"90 or less",IF(E74<=105,"91-105",IF(E74<=120,"106-120",IF(E74<=140,"121-140","Over 140")))) | Q74: =INT(C74/10)*10
A75: 75 | B75: Elmer Gantry | C75: 1960 | D75: USA | E75: 146 | F75: English | G75: Approved | H75: 25529690 | I75: 3000000 | J75: =IF(OR(H75="",H75=25529689.5),"Yes","No") | K75: =IF(AND(D75="USA",C75>=1980,J75="No"),"Yes","No") | L75: =IF(J75="Yes","",H75-I75) | M75: =IF(OR(J75="Yes",I75=0),"",H75/I75) | N75: =IF(J75="Yes","",IF(H75>=I75,1,0)) | O75: =IF(I75<=5000000,"Under $5M",IF(I75<=20000000,"$5M-20M",IF(I75<=50000000,"$20M-50M",IF(I75<=100000000,"$50M-100M","$100M+")))) | P75: =IF(E75<=90,"90 or less",IF(E75<=105,"91-105",IF(E75<=120,"106-120",IF(E75<=140,"121-140","Over 140")))) | Q75: =INT(C75/10)*10
A76: 76 | B76: Psycho | C76: 1960 | D76: USA | E76: 108 | F76: English | G76: R | H76: 32000000 | I76: 806947 | J76: =IF(OR(H76="",H76=25529689.5),"Yes","No") | K76: =IF(AND(D76="USA",C76>=1980,J76="No"),"Yes","No") | L76: =IF(J76="Yes","",H76-I76) | M76: =IF(OR(J76="Yes",I76=0),"",H76/I76) | N76: =IF(J76="Yes","",IF(H76>=I76,1,0)) | O76: =IF(I76<=5000000,"Under $5M",IF(I76<=20000000,"$5M-20M",IF(I76<=50000000,"$20M-50M",IF(I76<=100000000,"$50M-100M","$100M+")))) | P76: =IF(E76<=90,"90 or less",IF(E76<=105,"91-105",IF(E76<=120,"106-120",IF(E76<=140,"121-140","Over 140")))) | Q76: =INT(C76/10)*10
A77: 77 | B77: The Apartment | C77: 1960 | D77: USA | E77: 125 | F77: English | G77: Approved | H77: 25529690 | I77: 3000000 | J77: =IF(OR(H77="",H77=25529689.5),"Yes","No") | K77: =IF(AND(D77="USA",C77>=1980,J77="No"),"Yes","No") | L77: =IF(J77="Yes","",H77-I77) | M77: =IF(OR(J77="Yes",I77=0),"",H77/I77) | N77: =IF(J77="Yes","",IF(H77>=I77,1,0)) | O77: =IF(I77<=5000000,"Under $5M",IF(I77<=20000000,"$5M-20M",IF(I77<=50000000,"$20M-50M",IF(I77<=100000000,"$50M-100M","$100M+")))) | P77: =IF(E77<=90,"90 or less",IF(E77<=105,"91-105",IF(E77<=120,"106-120",IF(E77<=140,"121-140","Over 140")))) | Q77: =INT(C77/10)*10
A78: 78 | B78: Judgment at Nuremberg | C78: 1961 | D78: USA | E78: 186 | F78: English | G78: Not Rated | H78: 25529690 | I78: 3000000 | J78: =IF(OR(H78="",H78=25529689.5),"Yes","No") | K78: =IF(AND(D78="USA",C78>=1980,J78="No"),"Yes","No") | L78: =IF(J78="Yes","",H78-I78) | M78: =IF(OR(J78="Yes",I78=0),"",H78/I78) | N78: =IF(J78="Yes","",IF(H78>=I78,1,0)) | O78: =IF(I78<=5000000,"Under $5M",IF(I78<=20000000,"$5M-20M",IF(I78<=50000000,"$20M-50M",IF(I78<=100000000,"$50M-100M","$100M+")))) | P78: =IF(E78<=90,"90 or less",IF(E78<=105,"91-105",IF(E78<=120,"106-120",IF(E78<=140,"121-140","Over 140")))) | Q78: =INT(C78/10)*10
A79: 79 | B79: Pocketful of Miracles | C79: 1961 | D79: USA | E79: 136 | F79: English | G79: Approved | H79: 25529690 | I79: 2900000 | J79: =IF(OR(H79="",H79=25529689.5),"Yes","No") | K79: =IF(AND(D79="USA",C79>=1980,J79="No"),"Yes","No") | L79: =IF(J79="Yes","",H79-I79) | M79: =IF(OR(J79="Yes",I79=0),"",H79/I79) | N79: =IF(J79="Yes","",IF(H79>=I79,1,0)) | O79: =IF(I79<=5000000,"Under $5M",IF(I79<=20000000,"$5M-20M",IF(I79<=50000000,"$20M-50M",IF(I79<=100000000,"$50M-100M","$100M+")))) | P79: =IF(E79<=90,"90 or less",IF(E79<=105,"91-105",IF(E79<=120,"106-120",IF(E79<=140,"121-140","Over 140")))) | Q79: =INT(C79/10)*10
A80: 80 | B80: The Hustler | C80: 1961 | D80: USA | E80: 134 | F80: English | G80: Unrated | H80: 25529690 | I80: 2000000 | J80: =IF(OR(H80="",H80=25529689.5),"Yes","No") | K80: =IF(AND(D80="USA",C80>=1980,J80="No"),"Yes","No") | L80: =IF(J80="Yes","",H80-I80) | M80: =IF(OR(J80="Yes",I80=0),"",H80/I80) | N80: =IF(J80="Yes","",IF(H80>=I80,1,0)) | O80: =IF(I80<=5000000,"Under $5M",IF(I80<=20000000,"$5M-20M",IF(I80<=50000000,"$20M-50M",IF(I80<=100000000,"$50M-100M","$100M+")))) | P80: =IF(E80<=90,"90 or less",IF(E80<=105,"91-105",IF(E80<=120,"106-120",IF(E80<=140,"121-140","Over 140")))) | Q80: =INT(C80/10)*10
A81: 81 | B81: The Misfits | C81: 1961 | D81: USA | E81: 120 | F81: English | G81: Approved | H81: 25529690 | I81: 4000000 | J81: =IF(OR(H81="",H81=25529689.5),"Yes","No") | K81: =IF(AND(D81="USA",C81>=1980,J81="No"),"Yes","No") | L81: =IF(J81="Yes","",H81-I81) | M81: =IF(OR(J81="Yes",I81=0),"",H81/I81) | N81: =IF(J81="Yes","",IF(H81>=I81,1,0)) | O81: =IF(I81<=5000000,"Under $5M",IF(I81<=20000000,"$5M-20M",IF(I81<=50000000,"$20M-50M",IF(I81<=100000000,"$50M-100M","$100M+")))) | P81: =IF(E81<=90,"90 or less",IF(E81<=105,"91-105",IF(E81<=120,"106-120",IF(E81<=140,"121-140","Over 140")))) | Q81: =INT(C81/10)*10
A82: 82 | B82: West Side Story | C82: 1961 | D82: USA | E82: 152 | F82: English | G82: Unrated | H82: 43650000 | I82: 6000000 | J82: =IF(OR(H82="",H82=25529689.5),"Yes","No") | K82: =IF(AND(D82="USA",C82>=1980,J82="No"),"Yes","No") | L82: =IF(J82="Yes","",H82-I82) | M82: =IF(OR(J82="Yes",I82=0),"",H82/I82) | N82: =IF(J82="Yes","",IF(H82>=I82,1,0)) | O82: =IF(I82<=5000000,"Under $5M",IF(I82<=20000000,"$5M-20M",IF(I82<=50000000,"$20M-50M",IF(I82<=100000000,"$50M-100M","$100M+")))) | P82: =IF(E82<=90,"90 or less",IF(E82<=105,"91-105",IF(E82<=120,"106-120",IF(E82<=140,"121-140","Over 140")))) | Q82: =INT(C82/10)*10
A83: 83 | B83: Dr. No | C83: 1962 | D83: UK | E83: 110 | F83: English | G83: Approved | H83: 16067035 | I83: 1100000 | J83: =IF(OR(H83="",H83=25529689.5),"Yes","No") | K83: =IF(AND(D83="USA",C83>=1980,J83="No"),"Yes","No") | L83: =IF(J83="Yes","",H83-I83) | M83: =IF(OR(J83="Yes",I83=0),"",H83/I83) | N83: =IF(J83="Yes","",IF(H83>=I83,1,0)) | O83: =IF(I83<=5000000,"Under $5M",IF(I83<=20000000,"$5M-20M",IF(I83<=50000000,"$20M-50M",IF(I83<=100000000,"$50M-100M","$100M+")))) | P83: =IF(E83<=90,"90 or less",IF(E83<=105,"91-105",IF(E83<=120,"106-120",IF(E83<=140,"121-140","Over 140")))) | Q83: =INT(C83/10)*10
A84: 84 | B84: Lawrence of Arabia | C84: 1962 | D84: UK | E84: 227 | F84: English | G84: PG | H84: 6000000 | I84: 15000000 | J84: =IF(OR(H84="",H84=25529689.5),"Yes","No") | K84: =IF(AND(D84="USA",C84>=1980,J84="No"),"Yes","No") | L84: =IF(J84="Yes","",H84-I84) | M84: =IF(OR(J84="Yes",I84=0),"",H84/I84) | N84: =IF(J84="Yes","",IF(H84>=I84,1,0)) | O84: =IF(I84<=5000000,"Under $5M",IF(I84<=20000000,"$5M-20M",IF(I84<=50000000,"$20M-50M",IF(I84<=100000000,"$50M-100M","$100M+")))) | P84: =IF(E84<=90,"90 or less",IF(E84<=105,"91-105",IF(E84<=120,"106-120",IF(E84<=140,"121-140","Over 140")))) | Q84: =INT(C84/10)*10
... A106: 107 | B106: The Train | C106: 1964 | D106: France | E106: 133 | F106: English | G106: Unrated | H106: 25529690 | I106: 6700000 | J106: =IF(OR(H106="",H106=25529689.5),"Yes","No") | K106: =IF(AND(D106="USA",C106>=1980,J106="No"),"Yes","No") | L106: =IF(J106="Yes","",H106-I106) | M106: =IF(OR(J106="Yes",I106=0),"",H106/I106) | N106: =IF(J106="Yes","",IF(H106>=I106,1,0)) | O106: =IF(I106<=5000000,"Under $5M",IF(I106<=20000000,"$5M-20M",IF(I106<=50000000,"$20M-50M",IF(I106<=100000000,"$50M-100M","$100M+")))) | P106: =IF(E106<=90,"90 or less",IF(E106<=105,"91-105",IF(E106<=120,"106-120",IF(E106<=140,"121-140","Over 140")))) | Q106: =INT(C106/10)*10
A107: 108 | B107: Une Femme MariÃ©e | C107: 1964 | D107: France | E107: 94 | F107: French | H107: 25529690 | I107: 120000 | J107: =IF(OR(H107="",H107=25529689.5),"Yes","No") | K107: =IF(AND(D107="USA",C107>=1980,J107="No"),"Yes","No") | L107: =IF(J107="Yes","",H107-I107) | M107: =IF(OR(J107="Yes",I107=0),"",H107/I107) | N107: =IF(J107="Yes","",IF(H107>=I107,1,0)) | O107: =IF(I107<=5000000,"Under $5M",IF(I107<=20000000,"$5M-20M",IF(I107<=50000000,"$20M-50M",IF(I107<=100000000,"$50M-100M","$100M+")))) | P107: =IF(E107<=90,"90 or less",IF(E107<=105,"91-105",IF(E107<=120,"106-120",IF(E107<=140,"121-140","Over 140")))) | Q107: =INT(C107/10)*10
A108: 109 | B108: Doctor Zhivago | C108: 1965 | D108: USA | E108: 200 | F108: English | G108: PG-13 | H108: 111722000 | I108: 11000000 | J108: =IF(OR(H108="",H108=25529689.5),"Yes","No") | K108: =IF(AND(D108="USA",C108>=1980,J108="No"),"Yes","No") | L108: =IF(J108="Yes","",H108-I108) | M108: =IF(OR(J108="Yes",I108=0),"",H108/I108) | N108: =IF(J108="Yes","",IF(H108>=I108,1,0)) | O108: =IF(I108<=5000000,"Under $5M",IF(I108<=20000000,"$5M-20M",IF(I108<=50000000,"$20M-50M",IF(I108<=100000000,"$50M-100M","$100M+")))) | P108: =IF(E108<=90,"90 or less",IF(E108<=105,"91-105",IF(E108<=120,"106-120",IF(E108<=140,"121-140","Over 140")))) | Q108: =INT(C108/10)*10
A109: 110 | B109: Major Dundee | C109: 1965 | D109: USA | E109: 152 | F109: English | G109: Approved | H109: 14873 | I109: 3800000 | J109: =IF(OR(H109="",H109=25529689.5),"Yes","No") | K109: =IF(AND(D109="USA",C109>=1980,J109="No"),"Yes","No") | L109: =IF(J109="Yes","",H109-I109) | M109: =IF(OR(J109="Yes",I109=0),"",H109/I109) | N109: =IF(J109="Yes","",IF(H109>=I109,1,0)) | O109: =IF(I109<=5000000,"Under $5M",IF(I109<=20000000,"$5M-20M",IF(I109<=50000000,"$20M-50M",IF(I109<=100000000,"$50M-100M","$100M+")))) | P109: =IF(E109<=90,"90 or less",IF(E109<=105,"91-105",IF(E109<=120,"106-120",IF(E109<=140,"121-140","Over 140")))) | Q109: =INT(C109/10)*10
A110: 111 | B110: Pierrot le Fou | C110: 1965 | D110: France | E110: 110 | F110: French | G110: Not Rated | H110: 25529690 | I110: 300000 | J110: =IF(OR(H110="",H110=25529689.5),"Yes","No") | K110: =IF(AND(D110="USA",C110>=1980,J110="No"),"Yes","No") | L110: =IF(J110="Yes","",H110-I110) | M110: =IF(OR(J110="Yes",I110=0),"",H110/I110) | N110: =IF(J110="Yes","",IF(H110>=I110,1,0)) | O110: =IF(I110<=5000000,"Under $5M",IF(I110<=20000000,"$5M-20M",IF(I110<=50000000,"$20M-50M",IF(I110<=100000000,"$50M-100M","$100M+")))) | P110: =IF(E110<=90,"90 or less",IF(E110<=105,"91-105",IF(E110<=120,"106-120",IF(E110<=140,"121-140","Over 140")))) | Q110: =INT(C110/10)*10
A111: 112 | B111: The Greatest Story Ever Told | C111: 1965 | D111: USA | E111: 225 | F111: English | G111: G | H111: 8000000 | I111: 20000000 | J111: =IF(OR(H111="",H111=25529689.5),"Yes","No") | K111: =IF(AND(D111="USA",C111>=1980,J111="No"),"Yes","No") | L111: =IF(J111="Yes","",H111-I111) | M111: =IF(OR(J111="Yes",I111=0),"",H111/I111) | N111: =IF(J111="Yes","",IF(H111>=I111,1,0)) | O111: =IF(I111<=5000000,"Under $5M",IF(I111<=20000000,"$5M-20M",IF(I111<=50000000,"$20M-50M",IF(I111<=100000000,"$50M-100M","$100M+")))) | P111: =IF(E111<=90,"90 or less",IF(E111<=105,"91-105",IF(E111<=120,"106-120",IF(E111<=140,"121-140","Over 140")))) | Q111: =INT(C111/10)*10
A112: 113 | B112: The Party's Over | C112: 1965 | D112: UK | E112: 94 | F112: English | H112: 25529690 | I112: 20000000 | J112: =IF(OR(H112="",H112=25529689.5),"Yes","No") | K112: =IF(AND(D112="USA",C112>=1980,J112="No"),"Yes","No") | L112: =IF(J112="Yes","",H112-I112) | M112: =IF(OR(J112="Yes",I112=0),"",H112/I112) | N112: =IF(J112="Yes","",IF(H112>=I112,1,0)) | O112: =IF(I112<=5000000,"Under $5M",IF(I112<=20000000,"$5M-20M",IF(I112<=50000000,"$20M-50M",IF(I112<=100000000,"$50M-100M","$100M+")))) | P112: =IF(E112<=90,"90 or less",IF(E112<=105,"91-105",IF(E112<=120,"106-120",IF(E112<=140,"121-140","Over 140")))) | Q112: =INT(C112/10)*10
A113: 114 | B113: The Sound of Music | C113: 1965 | D113: USA | E113: 174 | F113: English | G113: G | H113: 163214286 | I113: 8200000 | J113: =IF(OR(H113="",H113=25529689.5),"Yes","No") | K113: =IF(AND(D113="USA",C113>=1980,J113="No"),"Yes","No") | L113: =IF(J113="Yes","",H113-I113) | M113: =IF(OR(J113="Yes",I113=0),"",H113/I113) | N113: =IF(J113="Yes","",IF(H113>=I113,1,0)) | O113: =IF(I113<=5000000,"Under $5M",IF(I113<=20000000,"$5M-20M",IF(I113<=50000000,"$20M-50M",IF(I113<=100000000,"$50M-100M","$100M+")))) | P113: =IF(E113<=90,"90 or less",IF(E113<=105,"91-105",IF(E113<=120,"106-120",IF(E113<=140,"121-140","Over 140")))) | Q113: =INT(C113/10)*10
A114: 115 | B114: Thunderball | C114: 1965 | D114: UK | E114: 130 | F114: English | G114: Approved | H114: 63600000 | I114: 9000000 | J114: =IF(OR(H114="",H114=25529689.5),"Yes","No") | K114: =IF(AND(D114="USA",C114>=1980,J114="No"),"Yes","No") | L114: =IF(J114="Yes","",H114-I114) | M114: =IF(OR(J114="Yes",I114=0),"",H114/I114) | N114: =IF(J114="Yes","",IF(H114>=I114,1,0)) | O114: =IF(I114<=5000000,"Under $5M",IF(I114<=20000000,"$5M-20M",IF(I114<=50000000,"$20M-50M",IF(I114<=100000000,"$50M-100M","$100M+")))) | P114: =IF(E114<=90,"90 or less",IF(E114<=105,"91-105",IF(E114<=120,"106-120",IF(E114<=140,"121-140","Over 140")))) | Q114: =INT(C114/10)*10
A115: 116 | B115: A Funny Thing Happened on the Way to the Forum | C115: 1966 | D115: USA | E115: 99 | F115: English | G115: Approved | H115: 25529690 | I115: 2000000 | J115: =IF(OR(H115="",H115=25529689.5),"Yes","No") | K115: =IF(AND(D115="USA",C115>=1980,J115="No"),"Yes","No") | L115: =IF(J115="Yes","",H115-I115) | M115: =IF(OR(J115="Yes",I115=0),"",H115/I115) | N115: =IF(J115="Yes","",IF(H115>=I115,1,0)) | O115: =IF(I115<=5000000,"Under $5M",IF(I115<=20000000,"$5M-20M",IF(I115<=50000000,"$20M-50M",IF(I115<=100000000,"$50M-100M","$100M+")))) | P115: =IF(E115<=90,"90 or less",IF(E115<=105,"91-105",IF(E115<=120,"106-120",IF(E115<=140,"121-140","Over 140")))) | Q115: =INT(C115/10)*10
A116: 117 | B116: A Man for All Seasons | C116: 1966 | D116: UK | E116: 120 | F116: English | G116: Approved | H116: 25529690 | I116: 2000000 | J116: =IF(OR(H116="",H116=25529689.5),"Yes","No") | K116: =IF(AND(D116="USA",C116>=1980,J116="No"),"Yes","No") | L116: =IF(J116="Yes","",H116-I116) | M116: =IF(OR(J116="Yes",I116=0),"",H116/I116) | N116: =IF(J116="Yes","",IF(H116>=I116,1,0)) | O116: =IF(I116<=5000000,"Under $5M",IF(I116<=20000000,"$5M-20M",IF(I116<=50000000,"$20M-50M",IF(I116<=100000000,"$50M-100M","$100M+")))) | P116: =IF(E116<=90,"90 or less",IF(E116<=105,"91-105",IF(E116<=120,"106-120",IF(E116<=140,"121-140","Over 140")))) | Q116: =INT(C116/10)*10
A117: 118 | B117: Batman: The Movie | C117: 1966 | D117: USA | E117: 105 | F117: English | G117: Approved | H117: 25529690 | I117: 1377800 | J117: =IF(OR(H117="",H117=25529689.5),"Yes","No") | K117: =IF(AND(D117="USA",C117>=1980,J117="No"),"Yes","No") | L117: =IF(J117="Yes","",H117-I117) | M117: =IF(OR(J117="Yes",I117=0),"",H117/I117) | N117: =IF(J117="Yes","",IF(H117>=I117,1,0)) | O117: =IF(I117<=5000000,"Under $5M",IF(I117<=20000000,"$5M-20M",IF(I117<=50000000,"$20M-50M",IF(I117<=100000000,"$50M-100M","$100M+")))) | P117: =IF(E117<=90,"90 or less",IF(E117<=105,"91-105",IF(E117<=120,"106-120",IF(E117<=140,"121-140","Over 140")))) | Q117: =INT(C117/10)*10
A118: 119 | B118: Harper | C118: 1966 | D118: USA | E118: 121 | F118: English | G118: Not Rated | H118: 25529690 | I118: 3500000 | J118: =IF(OR(H118="",H118=25529689.5),"Yes","No") | K118: =IF(AND(D118="USA",C118>=1980,J118="No"),"Yes","No") | L118: =IF(J118="Yes","",H118-I118) | M118: =IF(OR(J118="Yes",I118=0),"",H118/I118) | N118: =IF(J118="Yes","",IF(H118>=I118,1,0)) | O118: =IF(I118<=5000000,"Under $5M",IF(I118<=20000000,"$5M-20M",IF(I118<=50000000,"$20M-50M",IF(I118<=100000000,"$50M-100M","$100M+")))) | P118: =IF(E118<=90,"90 or less",IF(E118<=105,"91-105",IF(E118<=120,"106-120",IF(E118<=140,"121-140","Over 140")))) | Q118: =INT(C118/10)*10
A119: 120 | B119: The Good, the Bad and the Ugly | C119: 1966 | D119: Italy | E119: 142 | F119: Italian | G119: Approved | H119: 6100000 | I119: 1200000 | J119: =IF(OR(H119="",H119=25529689.5),"Yes","No") | K119: =IF(AND(D119="USA",C119>=1980,J119="No"),"Yes","No") | L119: =IF(J119="Yes","",H119-I119) | M119: =IF(OR(J119="Yes",I119=0),"",H119/I119) | N119: =IF(J119="Yes","",IF(H119>=I119,1,0)) | O119: =IF(I119<=5000000,"Under $5M",IF(I119<=20000000,"$5M-20M",IF(I119<=50000000,"$20M-50M",IF(I119<=100000000,"$50M-100M","$100M+")))) | P119: =IF(E119<=90,"90 or less",IF(E119<=105,"91-105",IF(E119<=120,"106-120",IF(E119<=140,"121-140","Over 140")))) | Q119: =INT(C119/10)*10
A120: 121 | B120: Torn Curtain | C120: 1966 | D120: USA | E120: 128 | F120: English | G120: Approved | H120: 25529690 | I120: 6000000 | J120: =IF(OR(H120="",H120=25529689.5),"Yes","No") | K120: =IF(AND(D120="USA",C120>=1980,J120="No"),"Yes","No") | L120: =IF(J120="Yes","",H120-I120) | M120: =IF(OR(J120="Yes",I120=0),"",H120/I120) | N120: =IF(J120="Yes","",IF(H120>=I120,1,0)) | O120: =IF(I120<=5000000,"Under $5M",IF(I120<=20000000,"$5M-20M",IF(I120<=50000000,"$20M-50M",IF(I120<=100000000,"$50M-100M","$100M+")))) | P120: =IF(E120<=90,"90 or less",IF(E120<=105,"91-105",IF(E120<=120,"106-120",IF(E120<=140,"121-140","Over 140")))) | Q120: =INT(C120/10)*10
A121: 122 | B121: In Cold Blood | C121: 1967 | D121: USA | E121: 134 | F121: English | G121: Approved | H121: 25529690 | I121: 3500000 | J121: =IF(OR(H121="",H121=25529689.5),"Yes","No") | K121: =IF(AND(D121="USA",C121>=1980,J121="No"),"Yes","No") | L121: =IF(J121="Yes","",H121-I121) | M121: =IF(OR(J121="Yes",I121=0),"",H121/I121) | N121: =IF(J121="Yes","",IF(H121>=I121,1,0)) | O121: =IF(I121<=5000000,"Under $5M",IF(I121<=20000000,"$5M-20M",IF(I121<=50000000,"$20M-50M",IF(I121<=100000000,"$50M-100M","$100M+")))) | P121: =IF(E121<=90,"90 or less",IF(E121<=105,"91-105",IF(E121<=120,"106-120",IF(E121<=140,"121-140","Over 140")))) | Q121: =INT(C121/10)*10
A122: 123 | B122: Point Blank | C122: 1967 | D122: USA | E122: 92 | F122: English | G122: Approved | H122: 25529690 | I122: 3000000 | J122: =IF(OR(H122="",H122=25529689.5),"Yes","No") | K122: =IF(AND(D122="USA",C122>=1980,J122="No"),"Yes","No") | L122: =IF(J122="Yes","",H122-I122) | M122: =IF(OR(J122="Yes",I122=0),"",H122/I122) | N122: =IF(J122="Yes","",IF(H122>=I122,1,0)) | O122: =IF(I122<=5000000,"Under $5M",IF(I122<=20000000,"$5M-20M",IF(I122<=50000000,"$20M-50M",IF(I122<=100000000,"$50M-100M","$100M+")))) | P122: =IF(E122<=90,"90 or less",IF(E122<=105,"91-105",IF(E122<=120,"106-120",IF(E122<=140,"121-140","Over 140")))) | Q122: =INT(C122/10)*10
A123: 124 | B123: The Torture Chamber of Dr. Sadism | C123: 1967 | D123: West Germany | E123: 80 | F123: German | G123: M | H123: 25529690 | I123: 20000000 | J123: =IF(OR(H123="",H123=25529689.5),"Yes","No") | K123: =IF(AND(D123="USA",C123>=1980,J123="No"),"Yes","No") | L123: =IF(J123="Yes","",H123-I123) | M123: =IF(OR(J123="Yes",I123=0),"",H123/I123) | N123: =IF(J123="Yes","",IF(H123>=I123,1,0)) | O123: =IF(I123<=5000000,"Under $5M",IF(I123<=20000000,"$5M-20M",IF(I123<=50000000,"$20M-50M",IF(I123<=100000000,"$50M-100M","$100M+")))) | P123: =IF(E123<=90,"90 or less",IF(E123<=105,"91-105",IF(E123<=120,"106-120",IF(E123<=140,"121-140","Over 140")))) | Q123: =INT(C123/10)*10
A124: 125 | B124: You Only Live Twice | C124: 1967 | D124: UK | E124: 117 | F124: English | G124: Approved | H124: 43100000 | I124: 9500000 | J124: =IF(OR(H124="",H124=25529689.5),"Yes","No") | K124: =IF(AND(D124="USA",C124>=1980,J124="No"),"Yes","No") | L124: =IF(J124="Yes","",H124-I124) | M124: =IF(OR(J124="Yes",I124=0),"",H124/I124) | N124: =IF(J124="Yes","",IF(H124>=I124,1,0)) | O124: =IF(I124<=5000000,"Under $5M",IF(I124<=20000000,"$5M-20M",IF(I124<=50000000,"$20M-50M",IF(I124<=100000000,"$50M-100M","$100M+")))) | P124: =IF(E124<=90,"90 or less",IF(E124<=105,"91-105",IF(E124<=120,"106-120",IF(E124<=140,"121-140","Over 140")))) | Q124: =INT(C124/10)*10
... A203: 207 | B203: Rocky | C203: 1976 | D203: USA | E203: 145 | F203: English | G203: PG | H203: 117235247 | I203: 960000 | J203: =IF(OR(H203="",H203=25529689.5),"Yes","No") | K203: =IF(AND(D203="USA",C203>=1980,J203="No"),"Yes","No") | L203: =IF(J203="Yes","",H203-I203) | M203: =IF(OR(J203="Yes",I203=0),"",H203/I203) | N203: =IF(J203="Yes","",IF(H203>=I203,1,0)) | O203: =IF(I203<=5000000,"Under $5M",IF(I203<=20000000,"$5M-20M",IF(I203<=50000000,"$20M-50M",IF(I203<=100000000,"$50M-100M","$100M+")))) | P203: =IF(E203<=90,"90 or less",IF(E203<=105,"91-105",IF(E203<=120,"106-120",IF(E203<=140,"121-140","Over 140")))) | Q203: =INT(C203/10)*10
A204: 208 | B204: Silent Movie | C204: 1976 | D204: USA | E204: 87 | G204: PG | H204: 25529690 | I204: 4400000 | J204: =IF(OR(H204="",H204=25529689.5),"Yes","No") | K204: =IF(AND(D204="USA",C204>=1980,J204="No"),"Yes","No") | L204: =IF(J204="Yes","",H204-I204) | M204: =IF(OR(J204="Yes",I204=0),"",H204/I204) | N204: =IF(J204="Yes","",IF(H204>=I204,1,0)) | O204: =IF(I204<=5000000,"Under $5M",IF(I204<=20000000,"$5M-20M",IF(I204<=50000000,"$20M-50M",IF(I204<=100000000,"$50M-100M","$100M+")))) | P204: =IF(E204<=90,"90 or less",IF(E204<=105,"91-105",IF(E204<=120,"106-120",IF(E204<=140,"121-140","Over 140")))) | Q204: =INT(C204/10)*10
A205: 209 | B205: Taxi Driver | C205: 1976 | D205: USA | E205: 110 | F205: English | G205: R | H205: 25529690 | I205: 1300000 | J205: =IF(OR(H205="",H205=25529689.5),"Yes","No") | K205: =IF(AND(D205="USA",C205>=1980,J205="No"),"Yes","No") | L205: =IF(J205="Yes","",H205-I205) | M205: =IF(OR(J205="Yes",I205=0),"",H205/I205) | N205: =IF(J205="Yes","",IF(H205>=I205,1,0)) | O205: =IF(I205<=5000000,"Under $5M",IF(I205<=20000000,"$5M-20M",IF(I205<=50000000,"$20M-50M",IF(I205<=100000000,"$50M-100M","$100M+")))) | P205: =IF(E205<=90,"90 or less",IF(E205<=105,"91-105",IF(E205<=120,"106-120",IF(E205<=140,"121-140","Over 140")))) | Q205: =INT(C205/10)*10
A206: 210 | B206: The Bad News Bears | C206: 1976 | D206: USA | E206: 102 | F206: English | G206: PG | H206: 25529690 | I206: 20000000 | J206: =IF(OR(H206="",H206=25529689.5),"Yes","No") | K206: =IF(AND(D206="USA",C206>=1980,J206="No"),"Yes","No") | L206: =IF(J206="Yes","",H206-I206) | M206: =IF(OR(J206="Yes",I206=0),"",H206/I206) | N206: =IF(J206="Yes","",IF(H206>=I206,1,0)) | O206: =IF(I206<=5000000,"Under $5M",IF(I206<=20000000,"$5M-20M",IF(I206<=50000000,"$20M-50M",IF(I206<=100000000,"$50M-100M","$100M+")))) | P206: =IF(E206<=90,"90 or less",IF(E206<=105,"91-105",IF(E206<=120,"106-120",IF(E206<=140,"121-140","Over 140")))) | Q206: =INT(C206/10)*10
A207: 211 | B207: The Omen | C207: 1976 | D207: UK | E207: 107 | F207: English | G207: R | H207: 25529690 | I207: 2800000 | J207: =IF(OR(H207="",H207=25529689.5),"Yes","No") | K207: =IF(AND(D207="USA",C207>=1980,J207="No"),"Yes","No") | L207: =IF(J207="Yes","",H207-I207) | M207: =IF(OR(J207="Yes",I207=0),"",H207/I207) | N207: =IF(J207="Yes","",IF(H207>=I207,1,0)) | O207: =IF(I207<=5000000,"Under $5M",IF(I207<=20000000,"$5M-20M",IF(I207<=50000000,"$20M-50M",IF(I207<=100000000,"$50M-100M","$100M+")))) | P207: =IF(E207<=90,"90 or less",IF(E207<=105,"91-105",IF(E207<=120,"106-120",IF(E207<=140,"121-140","Over 140")))) | Q207: =INT(C207/10)*10
A208: 213 | B208: A Bridge Too Far | C208: 1977 | D208: USA | E208: 175 | F208: English | G208: PG | H208: 50800000 | I208: 26000000 | J208: =IF(OR(H208="",H208=25529689.5),"Yes","No") | K208: =IF(AND(D208="USA",C208>=1980,J208="No"),"Yes","No") | L208: =IF(J208="Yes","",H208-I208) | M208: =IF(OR(J208="Yes",I208=0),"",H208/I208) | N208: =IF(J208="Yes","",IF(H208>=I208,1,0)) | O208: =IF(I208<=5000000,"Under $5M",IF(I208<=20000000,"$5M-20M",IF(I208<=50000000,"$20M-50M",IF(I208<=100000000,"$50M-100M","$100M+")))) | P208: =IF(E208<=90,"90 or less",IF(E208<=105,"91-105",IF(E208<=120,"106-120",IF(E208<=140,"121-140","Over 140")))) | Q208: =INT(C208/10)*10
A209: 214 | B209: Annie Hall | C209: 1977 | D209: USA | E209: 93 | F209: English | G209: PG | H209: 39200000 | I209: 4000000 | J209: =IF(OR(H209="",H209=25529689.5),"Yes","No") | K209: =IF(AND(D209="USA",C209>=1980,J209="No"),"Yes","No") | L209: =IF(J209="Yes","",H209-I209) | M209: =IF(OR(J209="Yes",I209=0),"",H209/I209) | N209: =IF(J209="Yes","",IF(H209>=I209,1,0)) | O209: =IF(I209<=5000000,"Under $5M",IF(I209<=20000000,"$5M-20M",IF(I209<=50000000,"$20M-50M",IF(I209<=100000000,"$50M-100M","$100M+")))) | P209: =IF(E209<=90,"90 or less",IF(E209<=105,"91-105",IF(E209<=120,"106-120",IF(E209<=140,"121-140","Over 140")))) | Q209: =INT(C209/10)*10
A210: 215 | B210: Capricorn One | C210: 1977 | D210: USA | E210: 130 | F210: English | G210: PG | H210: 25529690 | I210: 5000000 | J210: =IF(OR(H210="",H210=25529689.5),"Yes","No") | K210: =IF(AND(D210="USA",C210>=1980,J210="No"),"Yes","No") | L210: =IF(J210="Yes","",H210-I210) | M210: =IF(OR(J210="Yes",I210=0),"",H210/I210) | N210: =IF(J210="Yes","",IF(H210>=I210,1,0)) | O210: =IF(I210<=5000000,"Under $5M",IF(I210<=20000000,"$5M-20M",IF(I210<=50000000,"$20M-50M",IF(I210<=100000000,"$50M-100M","$100M+")))) | P210: =IF(E210<=90,"90 or less",IF(E210<=105,"91-105",IF(E210<=120,"106-120",IF(E210<=140,"121-140","Over 140")))) | Q210: =INT(C210/10)*10
A211: 216 | B211: Close Encounters of the Third Kind | C211: 1977 | D211: USA | E211: 135 | F211: English | G211: PG | H211: 128300000 | I211: 19400870 | J211: =IF(OR(H211="",H211=25529689.5),"Yes","No") | K211: =IF(AND(D211="USA",C211>=1980,J211="No"),"Yes","No") | L211: =IF(J211="Yes","",H211-I211) | M211: =IF(OR(J211="Yes",I211=0),"",H211/I211) | N211: =IF(J211="Yes","",IF(H211>=I211,1,0)) | O211: =IF(I211<=5000000,"Under $5M",IF(I211<=20000000,"$5M-20M",IF(I211<=50000000,"$20M-50M",IF(I211<=100000000,"$50M-100M","$100M+")))) | P211: =IF(E211<=90,"90 or less",IF(E211<=105,"91-105",IF(E211<=120,"106-120",IF(E211<=140,"121-140","Over 140")))) | Q211: =INT(C211/10)*10
A212: 217 | B212: Damnation Alley | C212: 1977 | D212: USA | E212: 91 | F212: English | G212: PG | H212: 25529690 | I212: 17000000 | J212: =IF(OR(H212="",H212=25529689.5),"Yes","No") | K212: =IF(AND(D212="USA",C212>=1980,J212="No"),"Yes","No") | L212: =IF(J212="Yes","",H212-I212) | M212: =IF(OR(J212="Yes",I212=0),"",H212/I212) | N212: =IF(J212="Yes","",IF(H212>=I212,1,0)) | O212: =IF(I212<=5000000,"Under $5M",IF(I212<=20000000,"$5M-20M",IF(I212<=50000000,"$20M-50M",IF(I212<=100000000,"$50M-100M","$100M+")))) | P212: =IF(E212<=90,"90 or less",IF(E212<=105,"91-105",IF(E212<=120,"106-120",IF(E212<=140,"121-140","Over 140")))) | Q212: =INT(C212/10)*10
A213: 218 | B213: Eraserhead | C213: 1977 | D213: USA | E213: 89 | F213: English | G213: Unrated | H213: 25529690 | I213: 20000 | J213: =IF(OR(H213="",H213=25529689.5),"Yes","No") | K213: =IF(AND(D213="USA",C213>=1980,J213="No"),"Yes","No") | L213: =IF(J213="Yes","",H213-I213) | M213: =IF(OR(J213="Yes",I213=0),"",H213/I213) | N213: =IF(J213="Yes","",IF(H213>=I213,1,0)) | O213: =IF(I213<=5000000,"Under $5M",IF(I213<=20000000,"$5M-20M",IF(I213<=50000000,"$20M-50M",IF(I213<=100000000,"$50M-100M","$100M+")))) | P213: =IF(E213<=90,"90 or less",IF(E213<=105,"91-105",IF(E213<=120,"106-120",IF(E213<=140,"121-140","Over 140")))) | Q213: =INT(C213/10)*10
A214: 219 | B214: Exorcist II: The Heretic | C214: 1977 | D214: USA | E214: 118 | F214: English | G214: R | H214: 25529690 | I214: 14000000 | J214: =IF(OR(H214="",H214=25529689.5),"Yes","No") | K214: =IF(AND(D214="USA",C214>=1980,J214="No"),"Yes","No") | L214: =IF(J214="Yes","",H214-I214) | M214: =IF(OR(J214="Yes",I214=0),"",H214/I214) | N214: =IF(J214="Yes","",IF(H214>=I214,1,0)) | O214: =IF(I214<=5000000,"Under $5M",IF(I214<=20000000,"$5M-20M",IF(I214<=50000000,"$20M-50M",IF(I214<=100000000,"$50M-100M","$100M+")))) | P214: =IF(E214<=90,"90 or less",IF(E214<=105,"91-105",IF(E214<=120,"106-120",IF(E214<=140,"121-140","Over 140")))) | Q214: =INT(C214/10)*10
A215: 220 | B215: High Anxiety | C215: 1977 | D215: USA | E215: 94 | F215: English | G215: PG | H215: 25529690 | I215: 3400000 | J215: =IF(OR(H215="",H215=25529689.5),"Yes","No") | K215: =IF(AND(D215="USA",C215>=1980,J215="No"),"Yes","No") | L215: =IF(J215="Yes","",H215-I215) | M215: =IF(OR(J215="Yes",I215=0),"",H215/I215) | N215: =IF(J215="Yes","",IF(H215>=I215,1,0)) | O215: =IF(I215<=5000000,"Under $5M",IF(I215<=20000000,"$5M-20M",IF(I215<=50000000,"$20M-50M",IF(I215<=100000000,"$50M-100M","$100M+")))) | P215: =IF(E215<=90,"90 or less",IF(E215<=105,"91-105",IF(E215<=120,"106-120",IF(E215<=140,"121-140","Over 140")))) | Q215: =INT(C215/10)*10
A216: 221 | B216: Julia | C216: 1977 | D216: USA | E216: 117 | F216: English | G216: PG | H216: 25529690 | I216: 7840000 | J216: =IF(OR(H216="",H216=25529689.5),"Yes","No") | K216: =IF(AND(D216="USA",C216>=1980,J216="No"),"Yes","No") | L216: =IF(J216="Yes","",H216-I216) | M216: =IF(OR(J216="Yes",I216=0),"",H216/I216) | N216: =IF(J216="Yes","",IF(H216>=I216,1,0)) | O216: =IF(I216<=5000000,"Under $5M",IF(I216<=20000000,"$5M-20M",IF(I216<=50000000,"$20M-50M",IF(I216<=100000000,"$50M-100M","$100M+")))) | P216: =IF(E216<=90,"90 or less",IF(E216<=105,"91-105",IF(E216<=120,"106-120",IF(E216<=140,"121-140","Over 140")))) | Q216: =INT(C216/10)*10
... A293: 302 | B293: Porky's | C293: 1981 | D293: Canada | E293: 94 | F293: English | G293: R | H293: 105500000 | I293: 4000000 | J293: =IF(OR(H293="",H293=25529689.5),"Yes","No") | K293: =IF(AND(D293="USA",C293>=1980,J293="No"),"Yes","No") | L293: =IF(J293="Yes","",H293-I293) | M293: =IF(OR(J293="Yes",I293=0),"",H293/I293) | N293: =IF(J293="Yes","",IF(H293>=I293,1,0)) | O293: =IF(I293<=5000000,"Under $5M",IF(I293<=20000000,"$5M-20M",IF(I293<=50000000,"$20M-50M",IF(I293<=100000000,"$50M-100M","$100M+")))) | P293: =IF(E293<=90,"90 or less",IF(E293<=105,"91-105",IF(E293<=120,"106-120",IF(E293<=140,"121-140","Over 140")))) | Q293: =INT(C293/10)*10
A294: 303 | B294: Quest for Fire | C294: 1981 | D294: Canada | E294: 100 | G294: R | H294: 25529690 | I294: 12500000 | J294: =IF(OR(H294="",H294=25529689.5),"Yes","No") | K294: =IF(AND(D294="USA",C294>=1980,J294="No"),"Yes","No") | L294: =IF(J294="Yes","",H294-I294) | M294: =IF(OR(J294="Yes",I294=0),"",H294/I294) | N294: =IF(J294="Yes","",IF(H294>=I294,1,0)) | O294: =IF(I294<=5000000,"Under $5M",IF(I294<=20000000,"$5M-20M",IF(I294<=50000000,"$20M-50M",IF(I294<=100000000,"$50M-100M","$100M+")))) | P294: =IF(E294<=90,"90 or less",IF(E294<=105,"91-105",IF(E294<=120,"106-120",IF(E294<=140,"121-140","Over 140")))) | Q294: =INT(C294/10)*10
A295: 304 | B295: Raiders of the Lost Ark | C295: 1981 | D295: USA | E295: 115 | F295: English | G295: PG | H295: 242374454 | I295: 18000000 | J295: =IF(OR(H295="",H295=25529689.5),"Yes","No") | K295: =IF(AND(D295="USA",C295>=1980,J295="No"),"Yes","No") | L295: =IF(J295="Yes","",H295-I295) | M295: =IF(OR(J295="Yes",I295=0),"",H295/I295) | N295: =IF(J295="Yes","",IF(H295>=I295,1,0)) | O295: =IF(I295<=5000000,"Under $5M",IF(I295<=20000000,"$5M-20M",IF(I295<=50000000,"$20M-50M",IF(I295<=100000000,"$50M-100M","$100M+")))) | P295: =IF(E295<=90,"90 or less",IF(E295<=105,"91-105",IF(E295<=120,"106-120",IF(E295<=140,"121-140","Over 140")))) | Q295: =INT(C295/10)*10
A296: 305 | B296: Reds | C296: 1981 | D296: USA | E296: 195 | F296: English | G296: PG | H296: 25529690 | I296: 35000000 | J296: =IF(OR(H296="",H296=25529689.5),"Yes","No") | K296: =IF(AND(D296="USA",C296>=1980,J296="No"),"Yes","No") | L296: =IF(J296="Yes","",H296-I296) | M296: =IF(OR(J296="Yes",I296=0),"",H296/I296) | N296: =IF(J296="Yes","",IF(H296>=I296,1,0)) | O296: =IF(I296<=5000000,"Under $5M",IF(I296<=20000000,"$5M-20M",IF(I296<=50000000,"$20M-50M",IF(I296<=100000000,"$50M-100M","$100M+")))) | P296: =IF(E296<=90,"90 or less",IF(E296<=105,"91-105",IF(E296<=120,"106-120",IF(E296<=140,"121-140","Over 140")))) | Q296: =INT(C296/10)*10
A297: 306 | B297: Roar | C297: 1981 | D297: USA | E297: 102 | F297: English | G297: PG | H297: 2000000 | I297: 17000000 | J297: =IF(OR(H297="",H297=25529689.5),"Yes","No") | K297: =IF(AND(D297="USA",C297>=1980,J297="No"),"Yes","No") | L297: =IF(J297="Yes","",H297-I297) | M297: =IF(OR(J297="Yes",I297=0),"",H297/I297) | N297: =IF(J297="Yes","",IF(H297>=I297,1,0)) | O297: =IF(I297<=5000000,"Under $5M",IF(I297<=20000000,"$5M-20M",IF(I297<=50000000,"$20M-50M",IF(I297<=100000000,"$50M-100M","$100M+")))) | P297: =IF(E297<=90,"90 or less",IF(E297<=105,"91-105",IF(E297<=120,"106-120",IF(E297<=140,"121-140","Over 140")))) | Q297: =INT(C297/10)*10
A298: 307 | B298: Sphinx | C298: 1981 | D298: USA | E298: 118 | F298: English | G298: PG | H298: 800000 | I298: 14000000 | J298: =IF(OR(H298="",H298=25529689.5),"Yes","No") | K298: =IF(AND(D298="USA",C298>=1980,J298="No"),"Yes","No") | L298: =IF(J298="Yes","",H298-I298) | M298: =IF(OR(J298="Yes",I298=0),"",H298/I298) | N298: =IF(J298="Yes","",IF(H298>=I298,1,0)) | O298: =IF(I298<=5000000,"Under $5M",IF(I298<=20000000,"$5M-20M",IF(I298<=50000000,"$20M-50M",IF(I298<=100000000,"$50M-100M","$100M+")))) | P298: =IF(E298<=90,"90 or less",IF(E298<=105,"91-105",IF(E298<=120,"106-120",IF(E298<=140,"121-140","Over 140")))) | Q298: =INT(C298/10)*10
A299: 308 | B299: Stripes | C299: 1981 | D299: USA | E299: 117 | F299: English | G299: R | H299: 85300000 | I299: 10000000 | J299: =IF(OR(H299="",H299=25529689.5),"Yes","No") | K299: =IF(AND(D299="USA",C299>=1980,J299="No"),"Yes","No") | L299: =IF(J299="Yes","",H299-I299) | M299: =IF(OR(J299="Yes",I299=0),"",H299/I299) | N299: =IF(J299="Yes","",IF(H299>=I299,1,0)) | O299: =IF(I299<=5000000,"Under $5M",IF(I299<=20000000,"$5M-20M",IF(I299<=50000000,"$20M-50M",IF(I299<=100000000,"$50M-100M","$100M+")))) | P299: =IF(E299<=90,"90 or less",IF(E299<=105,"91-105",IF(E299<=120,"106-120",IF(E299<=140,"121-140","Over 140")))) | Q299: =INT(C299/10)*10
A300: 309 | B300: The Beyond | C300: 1981 | D300: Italy | E300: 82 | F300: Italian | G300: X | H300: 126387 | I300: 400000 | J300: =IF(OR(H300="",H300=25529689.5),"Yes","No") | K300: =IF(AND(D300="USA",C300>=1980,J300="No"),"Yes","No") | L300: =IF(J300="Yes","",H300-I300) | M300: =IF(OR(J300="Yes",I300=0),"",H300/I300) | N300: =IF(J300="Yes","",IF(H300>=I300,1,0)) | O300: =IF(I300<=5000000,"Under $5M",IF(I300<=20000000,"$5M-20M",IF(I300<=50000000,"$20M-50M",IF(I300<=100000000,"$50M-100M","$100M+")))) | P300: =IF(E300<=90,"90 or less",IF(E300<=105,"91-105",IF(E300<=120,"106-120",IF(E300<=140,"121-140","Over 140")))) | Q300: =INT(C300/10)*10
A301: 310 | B301: The Evil Dead | C301: 1981 | D301: USA | E301: 96 | F301: English | G301: NC-17 | H301: 25529690 | I301: 375000 | J301: =IF(OR(H301="",H301=25529689.5),"Yes","No") | K301: =IF(AND(D301="USA",C301>=1980,J301="No"),"Yes","No") | L301: =IF(J301="Yes","",H301-I301) | M301: =IF(OR(J301="Yes",I301=0),"",H301/I301) | N301: =IF(J301="Yes","",IF(H301>=I301,1,0)) | O301: =IF(I301<=5000000,"Under $5M",IF(I301<=20000000,"$5M-20M",IF(I301<=50000000,"$20M-50M",IF(I301<=100000000,"$50M-100M","$100M+")))) | P301: =IF(E301<=90,"90 or less",IF(E301<=105,"91-105",IF(E301<=120,"106-120",IF(E301<=140,"121-140","Over 140")))) | Q301: =INT(C301/10)*10
A302: 311 | B302: The Four Seasons | C302: 1981 | D302: USA | E302: 107 | F302: English | G302: PG | H302: 25529690 | I302: 20000000 | J302: =IF(OR(H302="",H302=25529689.5),"Yes","No") | K302: =IF(AND(D302="USA",C302>=1980,J302="No"),"Yes","No") | L302: =IF(J302="Yes","",H302-I302) | M302: =IF(OR(J302="Yes",I302=0),"",H302/I302) | N302: =IF(J302="Yes","",IF(H302>=I302,1,0)) | O302: =IF(I302<=5000000,"Under $5M",IF(I302<=20000000,"$5M-20M",IF(I302<=50000000,"$20M-50M",IF(I302<=100000000,"$50M-100M","$100M+")))) | P302: =IF(E302<=90,"90 or less",IF(E302<=105,"91-105",IF(E302<=120,"106-120",IF(E302<=140,"121-140","Over 140")))) | Q302: =INT(C302/10)*10
A303: 312 | B303: The Howling | C303: 1981 | D303: USA | E303: 91 | F303: English | G303: R | H303: 17986000 | I303: 1000000 | J303: =IF(OR(H303="",H303=25529689.5),"Yes","No") | K303: =IF(AND(D303="USA",C303>=1980,J303="No"),"Yes","No") | L303: =IF(J303="Yes","",H303-I303) | M303: =IF(OR(J303="Yes",I303=0),"",H303/I303) | N303: =IF(J303="Yes","",IF(H303>=I303,1,0)) | O303: =IF(I303<=5000000,"Under $5M",IF(I303<=20000000,"$5M-20M",IF(I303<=50000000,"$20M-50M",IF(I303<=100000000,"$50M-100M","$100M+")))) | P303: =IF(E303<=90,"90 or less",IF(E303<=105,"91-105",IF(E303<=120,"106-120",IF(E303<=140,"121-140","Over 140")))) | Q303: =INT(C303/10)*10
A304: 313 | B304: The Legend of the Lone Ranger | C304: 1981 | D304: USA | E304: 98 | F304: English | G304: PG | H304: 8000000 | I304: 18000000 | J304: =IF(OR(H304="",H304=25529689.5),"Yes","No") | K304: =IF(AND(D304="USA",C304>=1980,J304="No"),"Yes","No") | L304: =IF(J304="Yes","",H304-I304) | M304: =IF(OR(J304="Yes",I304=0),"",H304/I304) | N304: =IF(J304="Yes","",IF(H304>=I304,1,0)) | O304: =IF(I304<=5000000,"Under $5M",IF(I304<=20000000,"$5M-20M",IF(I304<=50000000,"$20M-50M",IF(I304<=100000000,"$50M-100M","$100M+")))) | P304: =IF(E304<=90,"90 or less",IF(E304<=105,"91-105",IF(E304<=120,"106-120",IF(E304<=140,"121-140","Over 140")))) | Q304: =INT(C304/10)*10
A305: 314 | B305: The Postman Always Rings Twice | C305: 1981 | D305: USA | E305: 122 | F305: English | G305: R | H305: 25529690 | I305: 12000000 | J305: =IF(OR(H305="",H305=25529689.5),"Yes","No") | K305: =IF(AND(D305="USA",C305>=1980,J305="No"),"Yes","No") | L305: =IF(J305="Yes","",H305-I305) | M305: =IF(OR(J305="Yes",I305=0),"",H305/I305) | N305: =IF(J305="Yes","",IF(H305>=I305,1,0)) | O305: =IF(I305<=5000000,"Under $5M",IF(I305<=20000000,"$5M-20M",IF(I305<=50000000,"$20M-50M",IF(I305<=100000000,"$50M-100M","$100M+")))) | P305: =IF(E305<=90,"90 or less",IF(E305<=105,"91-105",IF(E305<=120,"106-120",IF(E305<=140,"121-140","Over 140")))) | Q305: =INT(C305/10)*10
A306: 315 | B306: The Pursuit of D.B. Cooper | C306: 1981 | D306: USA | E306: 100 | F306: English | G306: PG | H306: 25529690 | I306: 12000000 | J306: =IF(OR(H306="",H306=25529689.5),"Yes","No") | K306: =IF(AND(D306="USA",C306>=1980,J306="No"),"Yes","No") | L306: =IF(J306="Yes","",H306-I306) | M306: =IF(OR(J306="Yes",I306=0),"",H306/I306) | N306: =IF(J306="Yes","",IF(H306>=I306,1,0)) | O306: =IF(I306<=5000000,"Under $5M",IF(I306<=20000000,"$5M-20M",IF(I306<=50000000,"$20M-50M",IF(I306<=100000000,"$50M-100M","$100M+")))) | P306: =IF(E306<=90,"90 or less",IF(E306<=105,"91-105",IF(E306<=120,"106-120",IF(E306<=140,"121-140","Over 140")))) | Q306: =INT(C306/10)*10
... A326: 340 | B326: Star Trek II: The Wrath of Khan | C326: 1982 | D326: USA | E326: 116 | F326: English | G326: PG | H326: 78900000 | I326: 11000000 | J326: =IF(OR(H326="",H326=25529689.5),"Yes","No") | K326: =IF(AND(D326="USA",C326>=1980,J326="No"),"Yes","No") | L326: =IF(J326="Yes","",H326-I326) | M326: =IF(OR(J326="Yes",I326=0),"",H326/I326) | N326: =IF(J326="Yes","",IF(H326>=I326,1,0)) | O326: =IF(I326<=5000000,"Under $5M",IF(I326<=20000000,"$5M-20M",IF(I326<=50000000,"$20M-50M",IF(I326<=100000000,"$50M-100M","$100M+")))) | P326: =IF(E326<=90,"90 or less",IF(E326<=105,"91-105",IF(E326<=120,"106-120",IF(E326<=140,"121-140","Over 140")))) | Q326: =INT(C326/10)*10
A327: 341 | B327: The Ballad of Gregorio Cortez | C327: 1982 | D327: USA | E327: 105 | F327: English | H327: 25529690 | I327: 1250000 | J327: =IF(OR(H327="",H327=25529689.5),"Yes","No") | K327: =IF(AND(D327="USA",C327>=1980,J327="No"),"Yes","No") | L327: =IF(J327="Yes","",H327-I327) | M327: =IF(OR(J327="Yes",I327=0),"",H327/I327) | N327: =IF(J327="Yes","",IF(H327>=I327,1,0)) | O327: =IF(I327<=5000000,"Under $5M",IF(I327<=20000000,"$5M-20M",IF(I327<=50000000,"$20M-50M",IF(I327<=100000000,"$50M-100M","$100M+")))) | P327: =IF(E327<=90,"90 or less",IF(E327<=105,"91-105",IF(E327<=120,"106-120",IF(E327<=140,"121-140","Over 140")))) | Q327: =INT(C327/10)*10
A328: 342 | B328: The Beastmaster | C328: 1982 | D328: USA | E328: 90 | F328: English | G328: PG | H328: 25529690 | I328: 8000000 | J328: =IF(OR(H328="",H328=25529689.5),"Yes","No") | K328: =IF(AND(D328="USA",C328>=1980,J328="No"),"Yes","No") | L328: =IF(J328="Yes","",H328-I328) | M328: =IF(OR(J328="Yes",I328=0),"",H328/I328) | N328: =IF(J328="Yes","",IF(H328>=I328,1,0)) | O328: =IF(I328<=5000000,"Under $5M",IF(I328<=20000000,"$5M-20M",IF(I328<=50000000,"$20M-50M",IF(I328<=100000000,"$50M-100M","$100M+")))) | P328: =IF(E328<=90,"90 or less",IF(E328<=105,"91-105",IF(E328<=120,"106-120",IF(E328<=140,"121-140","Over 140")))) | Q328: =INT(C328/10)*10
...
